{
    "chess_daily": {
        "last": {
            "rating": 1820,
            "date": 1751789383,
            "rd": 169
        },
        "best": {
            "rating": 1820,
            "date": 1751789383,
            "game": "https://www.chess.com/game/daily/825255028"
        },
        "record": {
            "win": 5,
            "loss": 0,
            "draw": 2,
            "time_per_move": 38791,
            "timeout_percent": 0
        }
    },
    "chess960_daily": {
        "last": {
            "rating": 1642,
            "date": 1693324378,
            "rd": 319
        },
        "best": {
            "rating": 1642,
            "date": 1693324378,
            "game": "https://www.chess.com/game/daily/498661103"
        },
        "record": {
            "win": 3,
            "loss": 0,
            "draw": 0,
            "time_per_move": 38791,
            "timeout_percent": 0
        }
    },
    "chess_rapid": {
        "last": {
            "rating": 2518,
            "date": 1705228406,
            "rd": 84
        },
        "best": {
            "rating": 2536,
            "date": 1693244426,
            "game": "https://www.chess.com/game/live/86978423829"
        },
        "record": {
            "win": 65,
            "loss": 21,
            "draw": 9
        }
    },
    "chess_bullet": {
        "last": {
            "rating": 3225,
            "date": 1765042221,
            "rd": 27
        },
        "best": {
            "rating": 3315,
            "date": 1752341439,
            "game": "https://www.chess.com/game/live/146654009791"
        },
        "record": {
            "win": 4353,
            "loss": 1918,
            "draw": 420
        }
    },
    "chess_blitz": {
        "last": {
            "rating": 3254,
            "date": 1765033681,
            "rd": 28
        },
        "best": {
            "rating": 3300,
            "date": 1763131625,
            "game": "https://www.chess.com/game/live/143320169752"
        },
        "record": {
            "win": 2834,
            "loss": 2254,
            "draw": 556
        }
    },
    "tactics": {
        "highest": {
            "rating": 2705,
            "date": 1761058994
        },
        "lowest": {
            "rating": 2705,
            "date": 1761058994
        }
    },
    "puzzle_rush": {
        "best": {
            "total_attempts": 79,
            "score": 76
        }
    }
}