{
    "games": [
        {
            "url": "https://www.chess.com/game/live/136020391942",
            "pgn": "[Event \"Live Chess\"]\n[Site \"Chess.com\"]\n[Date \"2025.03.07\"]\n[Round \"-\"]\n[White \"Shelly_C\"]\n[Black \"Jorgepr1\"]\n[Result \"1-0\"]\n[CurrentPosition \"5R2/8/8/4pP1k/8/2P1B3/4K3/8 b - -\"]\n[Timezone \"UTC\"]\n[ECO \"D02\"]\n[ECOUrl \"https://www.chess.com/openings/Queens-Pawn-Opening-Zukertort-Chigorin-Variation-3.e3-Bg4\"]\n[UTCDate \"2025.03.07\"]\n[UTCTime \"22:48:51\"]\n[WhiteElo \"899\"]\n[BlackElo \"906\"]\n[TimeControl \"60\"]\n[Termination \"Shelly_C won on time\"]\n[StartTime \"22:48:51\"]\n[EndDate \"2025.03.07\"]\n[EndTime \"22:51:05\"]\n[Link \"https://www.chess.com/game/live/136020391942\"]\n\n1. Nf3 {[%clk 0:00:59.8]} 1... d5 {[%clk 0:00:58.7]} 2. d4 {[%clk 0:00:59.3]} 2... Nc6 {[%clk 0:00:58.1]} 3. e3 {[%clk 0:00:59.2]} 3... Bg4 {[%clk 0:00:57.3]} 4. Bd3 {[%clk 0:00:59.1]} 4... f6 {[%clk 0:00:56.4]} 5. Nbd2 {[%clk 0:00:57.4]} 5... e5 {[%clk 0:00:55.8]} 6. h3 {[%clk 0:00:56.2]} 6... Bh5 {[%clk 0:00:54.4]} 7. g4 {[%clk 0:00:55]} 7... Bf7 {[%clk 0:00:52.9]} 8. e4 {[%clk 0:00:53.2]} 8... dxe4 {[%clk 0:00:50.9]} 9. Nxe4 {[%clk 0:00:52.5]} 9... Nxd4 {[%clk 0:00:48.6]} 10. Nxd4 {[%clk 0:00:50.7]} 10... Qxd4 {[%clk 0:00:48.5]} 11. c3 {[%clk 0:00:50]} 11... Qd7 {[%clk 0:00:45.9]} 12. Qe2 {[%clk 0:00:48.7]} 12... O-O-O {[%clk 0:00:45.2]} 13. Be3 {[%clk 0:00:47.7]} 13... Bd6 {[%clk 0:00:43.3]} 14. Nxd6+ {[%clk 0:00:45.4]} 14... Qxd6 {[%clk 0:00:40.9]} 15. O-O-O {[%clk 0:00:43.9]} 15... Qe6 {[%clk 0:00:37]} 16. Bxa7 {[%clk 0:00:42.4]} 16... Qxa2 {[%clk 0:00:35.2]} 17. Be3 {[%clk 0:00:39.8]} 17... Qa1+ {[%clk 0:00:33.5]} 18. Kc2 {[%clk 0:00:38.9]} 18... Qa4+ {[%clk 0:00:31.9]} 19. b3 {[%clk 0:00:37.7]} 19... Bxb3+ {[%clk 0:00:28.7]} 20. Kc1 {[%clk 0:00:34.7]} 20... Qa1+ {[%clk 0:00:26.5]} 21. Kd2 {[%clk 0:00:33.3]} 21... Qa2+ {[%clk 0:00:25]} 22. Ke1 {[%clk 0:00:32.3]} 22... Bxd1 {[%clk 0:00:23.7]} 23. Kxd1 {[%clk 0:00:30.8]} 23... Qxe2+ {[%clk 0:00:21.6]} 24. Kxe2 {[%clk 0:00:30.7]} 24... Rd6 {[%clk 0:00:20.1]} 25. Bf5+ {[%clk 0:00:29.8]} 25... Kd8 {[%clk 0:00:16.2]} 26. Bc5 {[%clk 0:00:29.2]} 26... Rc6 {[%clk 0:00:13.7]} 27. Rd1+ {[%clk 0:00:28.3]} 27... Ke8 {[%clk 0:00:12.9]} 28. Bd7+ {[%clk 0:00:25.3]} 28... Kf7 {[%clk 0:00:11.6]} 29. Bxc6 {[%clk 0:00:24.7]} 29... bxc6 {[%clk 0:00:11.2]} 30. Rd7+ {[%clk 0:00:23.1]} 30... Ne7 {[%clk 0:00:10.8]} 31. Rxe7+ {[%clk 0:00:21.9]} 31... Kg6 {[%clk 0:00:09]} 32. h4 {[%clk 0:00:19.4]} 32... Rd8 {[%clk 0:00:08.1]} 33. h5+ {[%clk 0:00:18.3]} 33... Kg5 {[%clk 0:00:07.2]} 34. Be3+ {[%clk 0:00:17.1]} 34... Kxg4 {[%clk 0:00:05.1]} 35. f3+ {[%clk 0:00:16.2]} 35... Kxh5 {[%clk 0:00:04.7]} 36. Rxg7 {[%clk 0:00:14.6]} 36... Kh4 {[%clk 0:00:04.3]} 37. Rxh7+ {[%clk 0:00:14]} 37... Kg3 {[%clk 0:00:02.4]} 38. Rxc7 {[%clk 0:00:13.1]} 38... Kh2 {[%clk 0:00:02]} 39. Rxc6 {[%clk 0:00:12.4]} 39... Kg3 {[%clk 0:00:01.9]} 40. Rxf6 {[%clk 0:00:11.6]} 40... Kh4 {[%clk 0:00:01.3]} 41. f4 {[%clk 0:00:09.6]} 41... Kh5 {[%clk 0:00:00.5]} 42. f5 {[%clk 0:00:08.7]} 42... Rf8 {[%clk 0:00:00.4]} 43. Rxf8 {[%clk 0:00:07.5]} 1-0\n",
            "time_control": "60",
            "end_time": 1741387865,
            "rated": true,
            "tcn": "gvZJlB5Qmu6Eft1Tbl0KpxENoEN1uCJClCQBvB7BksBZdm86cu9RCRZRecRSuWSiWuiackayjr1rkcyaclailerdedimdm7RtL67uIRQhd78LZ81ZQXQdZ!0Z01UxF?7FNUMIuMEnvEN02NF23Fw3YwpYQpwQTwFvDFNDL79T9",
            "uuid": "57235245-fba6-11ef-ba3e-a318ff01000f",
            "initial_setup": "rnbqkbnr/pppppppp/8/8/8/8/PPPPPPPP/RNBQKBNR w KQkq - 0 1",
            "fen": "5R2/8/8/4pP1k/8/2P1B3/4K3/8 b - -",
            "time_class": "bullet",
            "rules": "chess",
            "white": {
                "rating": 899,
                "result": "win",
                "@id": "https://api.chess.com/pub/player/shelly_c",
                "username": "Shelly_C",
                "uuid": "e6624c4e-4a13-11ef-bf9d-9321e5ace9e6"
            },
            "black": {
                "rating": 906,
                "result": "timeout",
                "@id": "https://api.chess.com/pub/player/jorgepr1",
                "username": "Jorgepr1",
                "uuid": "22e90e32-1d95-11eb-989c-891235857dcd"
            },
            "eco": "https://www.chess.com/openings/Queens-Pawn-Opening-Zukertort-Chigorin-Variation-3.e3-Bg4"
        },
        {
            "url": "https://www.chess.com/game/live/136020452842",
            "pgn": "[Event \"Live Chess\"]\n[Site \"Chess.com\"]\n[Date \"2025.03.07\"]\n[Round \"-\"]\n[White \"Jorgepr1\"]\n[Black \"jasparovk\"]\n[Result \"0-1\"]\n[CurrentPosition \"8/pkp3p1/1p6/6N1/8/7P/P5qr/6K1 w - -\"]\n[Timezone \"UTC\"]\n[ECO \"C50\"]\n[ECOUrl \"https://www.chess.com/openings/Italian-Game-3...d6-4.c3\"]\n[UTCDate \"2025.03.07\"]\n[UTCTime \"22:51:26\"]\n[WhiteElo \"898\"]\n[BlackElo \"907\"]\n[TimeControl \"60\"]\n[Termination \"jasparovk won by checkmate\"]\n[StartTime \"22:51:26\"]\n[EndDate \"2025.03.07\"]\n[EndTime \"22:53:32\"]\n[Link \"https://www.chess.com/game/live/136020452842\"]\n\n1. e4 {[%clk 0:00:59.9]} 1... e5 {[%clk 0:00:58.4]} 2. Nf3 {[%clk 0:00:59.4]} 2... d6 {[%clk 0:00:58]} 3. Bc4 {[%clk 0:00:58.9]} 3... Nc6 {[%clk 0:00:57.6]} 4. c3 {[%clk 0:00:58.2]} 4... Be6 {[%clk 0:00:57.1]} 5. Bb3 {[%clk 0:00:56.2]} 5... Bxb3 {[%clk 0:00:54.6]} 6. Qxb3 {[%clk 0:00:56.1]} 6... b6 {[%clk 0:00:51.6]} 7. O-O {[%clk 0:00:54.1]} 7... Nf6 {[%clk 0:00:51.1]} 8. d3 {[%clk 0:00:53.1]} 8... Qd7 {[%clk 0:00:50.5]} 9. Bg5 {[%clk 0:00:52.6]} 9... Be7 {[%clk 0:00:48.3]} 10. Nbd2 {[%clk 0:00:51.8]} 10... O-O-O {[%clk 0:00:47.8]} 11. Rfe1 {[%clk 0:00:48.5]} 11... Kb7 {[%clk 0:00:47.2]} 12. d4 {[%clk 0:00:47.6]} 12... exd4 {[%clk 0:00:45.6]} 13. cxd4 {[%clk 0:00:46.6]} 13... d5 {[%clk 0:00:40.4]} 14. Bxf6 {[%clk 0:00:39.7]} 14... Bxf6 {[%clk 0:00:38.8]} 15. exd5 {[%clk 0:00:39.1]} 15... Na5 {[%clk 0:00:37.8]} 16. Qe3 {[%clk 0:00:35.5]} 16... Qxd5 {[%clk 0:00:36.3]} 17. Nb3 {[%clk 0:00:33.5]} 17... Nxb3 {[%clk 0:00:34.7]} 18. Qxb3 {[%clk 0:00:29.9]} 18... Qh5 {[%clk 0:00:29.2]} 19. Qxf7 {[%clk 0:00:25.3]} 19... Qg4 {[%clk 0:00:24]} 20. Qb3 {[%clk 0:00:20.7]} 20... Bxd4 {[%clk 0:00:22.5]} 21. Rad1 {[%clk 0:00:17.9]} 21... Bc5 {[%clk 0:00:20.3]} 22. Qe3 {[%clk 0:00:15.9]} 22... Bxe3 {[%clk 0:00:18.6]} 23. Rxe3 {[%clk 0:00:14.8]} 23... Rxd1+ {[%clk 0:00:17.1]} 24. Re1 {[%clk 0:00:12.7]} 24... Rxe1+ {[%clk 0:00:16]} 25. Nxe1 {[%clk 0:00:12.6]} 25... Qe2 {[%clk 0:00:14.2]} 26. Nf3 {[%clk 0:00:11.2]} 26... Qxb2 {[%clk 0:00:12.7]} 27. h3 {[%clk 0:00:10.1]} 27... Rd8 {[%clk 0:00:10.7]} 28. Kh2 {[%clk 0:00:09.4]} 28... Rd1 {[%clk 0:00:09.3]} 29. Ng5 {[%clk 0:00:08.5]} 29... Rd2 {[%clk 0:00:08.3]} 30. Nxh7 {[%clk 0:00:08]} 30... Rxf2 {[%clk 0:00:07.4]} 31. Ng5 {[%clk 0:00:07.4]} 31... Rxg2+ {[%clk 0:00:06.5]} 32. Kh1 {[%clk 0:00:06.4]} 32... Rh2+ {[%clk 0:00:05.6]} 33. Kg1 {[%clk 0:00:05.8]} 33... Qg2# {[%clk 0:00:04.9]} 0-1\n",
            "time_control": "60",
            "end_time": 1741388012,
            "rated": true,
            "tcn": "mC0KgvZRfA5Qks6SArSrdrXPeg!Tlt7ZcM90bl86fe6XtBKBsBRJMT0TCJQGruZJlrGrurJNr1NE1rTBadBIruIueu7duedeveEmevmjpx?7gp7dvMdlM3ln3Mnophophgjo",
            "uuid": "b37ed088-fba6-11ef-98f2-8bcf2701000f",
            "initial_setup": "rnbqkbnr/pppppppp/8/8/8/8/PPPPPPPP/RNBQKBNR w KQkq - 0 1",
            "fen": "8/pkp3p1/1p6/6N1/8/7P/P5qr/6K1 w - -",
            "time_class": "bullet",
            "rules": "chess",
            "white": {
                "rating": 898,
                "result": "checkmated",
                "@id": "https://api.chess.com/pub/player/jorgepr1",
                "username": "Jorgepr1",
                "uuid": "22e90e32-1d95-11eb-989c-891235857dcd"
            },
            "black": {
                "rating": 907,
                "result": "win",
                "@id": "https://api.chess.com/pub/player/jasparovk",
                "username": "jasparovk",
                "uuid": "854614be-e41d-11ef-ac13-df265798d17b"
            },
            "eco": "https://www.chess.com/openings/Italian-Game-3...d6-4.c3"
        },
        {
            "url": "https://www.chess.com/game/live/136020504516",
            "pgn": "[Event \"Live Chess\"]\n[Site \"Chess.com\"]\n[Date \"2025.03.07\"]\n[Round \"-\"]\n[White \"Jorgepr1\"]\n[Black \"Touitousohaib\"]\n[Result \"0-1\"]\n[CurrentPosition \"r1b2rk1/4ppbp/6p1/2p3B1/Pp2P1n1/1B1P1Q2/1P3PPq/R4RK1 w - -\"]\n[Timezone \"UTC\"]\n[ECO \"B30\"]\n[ECOUrl \"https://www.chess.com/openings/Sicilian-Defense-Old-Sicilian-Variation-3.Bc4\"]\n[UTCDate \"2025.03.07\"]\n[UTCTime \"22:53:39\"]\n[WhiteElo \"890\"]\n[BlackElo \"892\"]\n[TimeControl \"60\"]\n[Termination \"Touitousohaib won by checkmate\"]\n[StartTime \"22:53:39\"]\n[EndDate \"2025.03.07\"]\n[EndTime \"22:54:49\"]\n[Link \"https://www.chess.com/game/live/136020504516\"]\n\n1. e4 {[%clk 0:00:59.8]} 1... c5 {[%clk 0:00:56.6]} 2. Nf3 {[%clk 0:00:58.6]} 2... Nc6 {[%clk 0:00:56.2]} 3. Bc4 {[%clk 0:00:58.1]} 3... g6 {[%clk 0:00:56]} 4. d3 {[%clk 0:00:57]} 4... Bg7 {[%clk 0:00:55.6]} 5. c3 {[%clk 0:00:56.3]} 5... d6 {[%clk 0:00:54.8]} 6. Be3 {[%clk 0:00:55.4]} 6... Nf6 {[%clk 0:00:52.6]} 7. O-O {[%clk 0:00:54.5]} 7... O-O {[%clk 0:00:52.1]} 8. Bg5 {[%clk 0:00:50.4]} 8... b5 {[%clk 0:00:51.7]} 9. Bb3 {[%clk 0:00:48.7]} 9... a5 {[%clk 0:00:48.7]} 10. a4 {[%clk 0:00:46.9]} 10... b4 {[%clk 0:00:46.6]} 11. cxb4 {[%clk 0:00:45.7]} 11... axb4 {[%clk 0:00:46.5]} 12. Nbd2 {[%clk 0:00:41.4]} 12... Ng4 {[%clk 0:00:45.6]} 13. Nc4 {[%clk 0:00:38.9]} 13... Nce5 {[%clk 0:00:42]} 14. Nxd6 {[%clk 0:00:30.6]} 14... Qxd6 {[%clk 0:00:39.5]} 15. Nxe5 {[%clk 0:00:27.8]} 15... Qxe5 {[%clk 0:00:38]} 16. Qf3 {[%clk 0:00:24.2]} 16... Qxh2# {[%clk 0:00:35.8]} 0-1\n",
            "time_control": "60",
            "end_time": 1741388089,
            "rated": true,
            "tcn": "mCYIgv5QfA2Ult92ksZRcu!Teg8!uMXHArWGiyHzszGzblTElAQKAR7RvKRKdvKp",
            "uuid": "02925841-fba7-11ef-bcba-e30dac01000f",
            "initial_setup": "rnbqkbnr/pppppppp/8/8/8/8/PPPPPPPP/RNBQKBNR w KQkq - 0 1",
            "fen": "r1b2rk1/4ppbp/6p1/2p3B1/Pp2P1n1/1B1P1Q2/1P3PPq/R4RK1 w - -",
            "time_class": "bullet",
            "rules": "chess",
            "white": {
                "rating": 890,
                "result": "checkmated",
                "@id": "https://api.chess.com/pub/player/jorgepr1",
                "username": "Jorgepr1",
                "uuid": "22e90e32-1d95-11eb-989c-891235857dcd"
            },
            "black": {
                "rating": 892,
                "result": "win",
                "@id": "https://api.chess.com/pub/player/touitousohaib",
                "username": "Touitousohaib",
                "uuid": "0af136e4-ca57-11ed-9719-79d6b080adcc"
            },
            "eco": "https://www.chess.com/openings/Sicilian-Defense-Old-Sicilian-Variation-3.Bc4"
        },
        {
            "url": "https://www.chess.com/game/live/136020545638",
            "pgn": "[Event \"Live Chess\"]\n[Site \"Chess.com\"]\n[Date \"2025.03.07\"]\n[Round \"-\"]\n[White \"HYTMJ\"]\n[Black \"Jorgepr1\"]\n[Result \"0-1\"]\n[CurrentPosition \"r7/ppp3k1/8/8/4Pp2/2KPbr2/P1P5/8 w - -\"]\n[Timezone \"UTC\"]\n[ECO \"C20\"]\n[ECOUrl \"https://www.chess.com/openings/Kings-Pawn-Opening-Leonardis-Variation\"]\n[UTCDate \"2025.03.07\"]\n[UTCTime \"22:55:24\"]\n[WhiteElo \"859\"]\n[BlackElo \"897\"]\n[TimeControl \"60\"]\n[Termination \"Jorgepr1 won on time\"]\n[StartTime \"22:55:24\"]\n[EndDate \"2025.03.07\"]\n[EndTime \"22:57:30\"]\n[Link \"https://www.chess.com/game/live/136020545638\"]\n\n1. e4 {[%clk 0:00:58.9]} 1... e5 {[%clk 0:00:59.3]} 2. d3 {[%clk 0:00:58.8]} 2... Nc6 {[%clk 0:00:58.6]} 3. Nc3 {[%clk 0:00:58.3]} 3... Bb4 {[%clk 0:00:57.2]} 4. Qd2 {[%clk 0:00:56.7]} 4... d6 {[%clk 0:00:56.6]} 5. Qd1 {[%clk 0:00:54.9]} 5... Nf6 {[%clk 0:00:55.2]} 6. Bd2 {[%clk 0:00:54.4]} 6... Be6 {[%clk 0:00:53.7]} 7. Nf3 {[%clk 0:00:54]} 7... O-O {[%clk 0:00:52.7]} 8. h4 {[%clk 0:00:52.1]} 8... h5 {[%clk 0:00:50.7]} 9. Be2 {[%clk 0:00:52]} 9... Qe7 {[%clk 0:00:49]} 10. Ng1 {[%clk 0:00:50.3]} 10... Rfd8 {[%clk 0:00:48.5]} 11. Bg5 {[%clk 0:00:48.5]} 11... d5 {[%clk 0:00:46.4]} 12. g4 {[%clk 0:00:42]} 12... hxg4 {[%clk 0:00:42.8]} 13. Bxg4 {[%clk 0:00:40.8]} 13... Bxg4 {[%clk 0:00:41.4]} 14. Qxg4 {[%clk 0:00:34.6]} 14... d4 {[%clk 0:00:40.9]} 15. Bxf6 {[%clk 0:00:33]} 15... Qxf6 {[%clk 0:00:38.3]} 16. O-O-O {[%clk 0:00:30.2]} 16... dxc3 {[%clk 0:00:37]} 17. bxc3 {[%clk 0:00:27.3]} 17... Bxc3 {[%clk 0:00:36.9]} 18. Nf3 {[%clk 0:00:24.1]} 18... Nd4 {[%clk 0:00:32.9]} 19. Nxd4 {[%clk 0:00:22.3]} 19... Bxd4 {[%clk 0:00:32.8]} 20. h5 {[%clk 0:00:21]} 20... Qf4+ {[%clk 0:00:26.1]} 21. Qxf4 {[%clk 0:00:19.7]} 21... exf4 {[%clk 0:00:26]} 22. f3 {[%clk 0:00:19]} 22... Be3+ {[%clk 0:00:24.9]} 23. Kb1 {[%clk 0:00:16.9]} 23... Rd6 {[%clk 0:00:23.8]} 24. Rh2 {[%clk 0:00:15.6]} 24... Rh6 {[%clk 0:00:23.1]} 25. Rh4 {[%clk 0:00:11.2]} 25... g6 {[%clk 0:00:19.7]} 26. Rg4 {[%clk 0:00:05.7]} 26... Kg7 {[%clk 0:00:17.5]} 27. hxg6 {[%clk 0:00:04.2]} 27... fxg6 {[%clk 0:00:15.8]} 28. Rxg6+ {[%clk 0:00:04.1]} 28... Rxg6 {[%clk 0:00:14.7]} 29. Re1 {[%clk 0:00:02.6]} 29... Rg1 {[%clk 0:00:12]} 30. Kb2 {[%clk 0:00:02.2]} 30... Rxe1 {[%clk 0:00:10.7]} 31. Kc3 {[%clk 0:00:02.1]} 31... Ra1 {[%clk 0:00:09.1]} 32. Kb2 {[%clk 0:00:01.1]} 32... Rh1 {[%clk 0:00:07.3]} 33. Kb3 {[%clk 0:00:00.4]} 33... Rf1 {[%clk 0:00:07.2]} 34. Kc3 {[%clk 0:00:00.1]} 34... Rxf3 {[%clk 0:00:07.1]} 0-1\n",
            "time_control": "60",
            "end_time": 1741388250,
            "rated": true,
            "tcn": "mC0Klt5Qbs9zdlZRld!Tcl6Sgv8!pF3Nfm70vg97lMRJoENEmESEdEJBMT0TecBsjszsgvQBvBsBFNTDEDKDnvBucb7RhpRVpF2UFE!2NU1UEUVUdeUgbjgejseasjahjrhfrsfv",
            "uuid": "416f7bd2-fba7-11ef-ba3e-a318ff01000f",
            "initial_setup": "rnbqkbnr/pppppppp/8/8/8/8/PPPPPPPP/RNBQKBNR w KQkq - 0 1",
            "fen": "r7/ppp3k1/8/8/4Pp2/2KPbr2/P1P5/8 w - -",
            "time_class": "bullet",
            "rules": "chess",
            "white": {
                "rating": 859,
                "result": "timeout",
                "@id": "https://api.chess.com/pub/player/hytmj",
                "username": "HYTMJ",
                "uuid": "5c35ec10-edcb-11ed-afc2-d566b8b01ab3"
            },
            "black": {
                "rating": 897,
                "result": "win",
                "@id": "https://api.chess.com/pub/player/jorgepr1",
                "username": "Jorgepr1",
                "uuid": "22e90e32-1d95-11eb-989c-891235857dcd"
            },
            "eco": "https://www.chess.com/openings/Kings-Pawn-Opening-Leonardis-Variation"
        },
        {
            "url": "https://www.chess.com/game/live/136020599188",
            "pgn": "[Event \"Live Chess\"]\n[Site \"Chess.com\"]\n[Date \"2025.03.07\"]\n[Round \"-\"]\n[White \"Jorgepr1\"]\n[Black \"Alejandro9812\"]\n[Result \"0-1\"]\n[CurrentPosition \"2rk4/3p3p/8/3Q1P2/1b4r1/1N2B3/p1P2PP1/K2R3R w - -\"]\n[Timezone \"UTC\"]\n[ECO \"C40\"]\n[ECOUrl \"https://www.chess.com/openings/Kings-Pawn-Opening-Kings-Knight-Variation\"]\n[UTCDate \"2025.03.07\"]\n[UTCTime \"22:57:44\"]\n[WhiteElo \"889\"]\n[BlackElo \"908\"]\n[TimeControl \"60\"]\n[Termination \"Alejandro9812 won on time\"]\n[StartTime \"22:57:44\"]\n[EndDate \"2025.03.07\"]\n[EndTime \"22:59:39\"]\n[Link \"https://www.chess.com/game/live/136020599188\"]\n\n1. e4 {[%clk 0:00:58.9]} 1... e5 {[%clk 0:00:59.3]} 2. Nf3 {[%clk 0:00:58.2]} 2... Qf6 {[%clk 0:00:58.8]} 3. Bc4 {[%clk 0:00:57.5]} 3... g5 {[%clk 0:00:58.2]} 4. h3 {[%clk 0:00:54.7]} 4... g4 {[%clk 0:00:57.7]} 5. hxg4 {[%clk 0:00:53.5]} 5... a6 {[%clk 0:00:56.3]} 6. d3 {[%clk 0:00:51.1]} 6... b5 {[%clk 0:00:55.7]} 7. Bb3 {[%clk 0:00:49.3]} 7... Bc5 {[%clk 0:00:55.2]} 8. Nc3 {[%clk 0:00:46.7]} 8... Nh6 {[%clk 0:00:53]} 9. Nd5 {[%clk 0:00:46.3]} 9... Qd6 {[%clk 0:00:51.6]} 10. Bxh6 {[%clk 0:00:45.2]} 10... c6 {[%clk 0:00:49.2]} 11. Bd2 {[%clk 0:00:41.2]} 11... cxd5 {[%clk 0:00:47.6]} 12. exd5 {[%clk 0:00:41.1]} 12... Rg8 {[%clk 0:00:45.6]} 13. Qe2 {[%clk 0:00:36.8]} 13... Rxg4 {[%clk 0:00:44.3]} 14. O-O-O {[%clk 0:00:33.7]} 14... e4 {[%clk 0:00:43.1]} 15. dxe4 {[%clk 0:00:32.1]} 15... f6 {[%clk 0:00:37.5]} 16. a3 {[%clk 0:00:31.2]} 16... Bb7 {[%clk 0:00:36.6]} 17. Bc3 {[%clk 0:00:30.5]} 17... a5 {[%clk 0:00:34.7]} 18. Kb1 {[%clk 0:00:26]} 18... b4 {[%clk 0:00:34]} 19. Bd2 {[%clk 0:00:23.6]} 19... bxa3 {[%clk 0:00:32.9]} 20. bxa3 {[%clk 0:00:21.2]} 20... a4 {[%clk 0:00:32.4]} 21. Bc4 {[%clk 0:00:18.3]} 21... f5 {[%clk 0:00:31.3]} 22. exf5+ {[%clk 0:00:16.5]} 22... Kd8 {[%clk 0:00:29.2]} 23. Qd3 {[%clk 0:00:11.7]} 23... Na6 {[%clk 0:00:25.1]} 24. Be3 {[%clk 0:00:11.1]} 24... Nb4 {[%clk 0:00:24.4]} 25. axb4 {[%clk 0:00:09.4]} 25... Bxb4 {[%clk 0:00:23.3]} 26. Nd4 {[%clk 0:00:06.1]} 26... a3 {[%clk 0:00:22.5]} 27. Nb3 {[%clk 0:00:04.6]} 27... a2+ {[%clk 0:00:21.8]} 28. Ka1 {[%clk 0:00:02.7]} 28... Bxd5 {[%clk 0:00:19]} 29. Bxd5 {[%clk 0:00:01.1]} 29... Qxd5 {[%clk 0:00:18.5]} 30. Qxd5 {[%clk 0:00:00.3]} 30... Rc8 {[%clk 0:00:17.4]} 0-1\n",
            "time_control": "60",
            "end_time": 1741388379,
            "rated": true,
            "tcn": "mC0Kgv7TfA2MpxMExEWOltXHAr9Ibs!VsJTRcVYQVlQJCJ?!dm!EecKCtC1Tiq6XlsOGcbHzslzqjqGyrATLCL87mt5OluOzqzIzvByqBrqibaXJAJRJtJ46",
            "uuid": "94899746-fba7-11ef-ac41-a9c46501000f",
            "initial_setup": "rnbqkbnr/pppppppp/8/8/8/8/PPPPPPPP/RNBQKBNR w KQkq - 0 1",
            "fen": "2rk4/3p3p/8/3Q1P2/1b4r1/1N2B3/p1P2PP1/K2R3R w - -",
            "time_class": "bullet",
            "rules": "chess",
            "white": {
                "rating": 889,
                "result": "timeout",
                "@id": "https://api.chess.com/pub/player/jorgepr1",
                "username": "Jorgepr1",
                "uuid": "22e90e32-1d95-11eb-989c-891235857dcd"
            },
            "black": {
                "rating": 908,
                "result": "win",
                "@id": "https://api.chess.com/pub/player/alejandro9812",
                "username": "Alejandro9812",
                "uuid": "9a09ac86-e287-11ef-aace-d37028f332fc"
            },
            "eco": "https://www.chess.com/openings/Kings-Pawn-Opening-Kings-Knight-Variation"
        },
        {
            "url": "https://www.chess.com/game/live/136022360006",
            "pgn": "[Event \"Live Chess\"]\n[Site \"Chess.com\"]\n[Date \"2025.03.08\"]\n[Round \"-\"]\n[White \"TH8577\"]\n[Black \"Jorgepr1\"]\n[Result \"1-0\"]\n[CurrentPosition \"8/8/6PK/k7/8/8/8/8 b - -\"]\n[Timezone \"UTC\"]\n[ECO \"D04\"]\n[ECOUrl \"https://www.chess.com/openings/Colle-System-Anti-Colle-Variation-4.Bd3-Bxd3-5.Qxd3\"]\n[UTCDate \"2025.03.08\"]\n[UTCTime \"00:21:44\"]\n[WhiteElo \"804\"]\n[BlackElo \"807\"]\n[TimeControl \"180\"]\n[Termination \"TH8577 won by resignation\"]\n[StartTime \"00:21:44\"]\n[EndDate \"2025.03.08\"]\n[EndTime \"00:26:46\"]\n[Link \"https://www.chess.com/game/live/136022360006\"]\n\n1. d4 {[%clk 0:02:59.8]} 1... d5 {[%clk 0:02:57.9]} 2. e3 {[%clk 0:02:59.1]} 2... Nf6 {[%clk 0:02:55.2]} 3. Nf3 {[%clk 0:02:58.5]} 3... Bf5 {[%clk 0:02:53.8]} 4. Bd3 {[%clk 0:02:57.2]} 4... Bxd3 {[%clk 0:02:51.3]} 5. Qxd3 {[%clk 0:02:56.4]} 5... e6 {[%clk 0:02:49.7]} 6. Ne5 {[%clk 0:02:55.6]} 6... c5 {[%clk 0:02:46.3]} 7. dxc5 {[%clk 0:02:54.5]} 7... Bxc5 {[%clk 0:02:42.1]} 8. Nc3 {[%clk 0:02:51.6]} 8... Bd6 {[%clk 0:02:35.8]} 9. Qb5+ {[%clk 0:02:43.4]} 9... Nbd7 {[%clk 0:02:25.4]} 10. Nxd7 {[%clk 0:02:39.8]} 10... Qxd7 {[%clk 0:02:25.3]} 11. Qxd7+ {[%clk 0:02:36.2]} 11... Nxd7 {[%clk 0:02:24.8]} 12. O-O {[%clk 0:02:35]} 12... O-O {[%clk 0:02:23.7]} 13. f3 {[%clk 0:02:33.1]} 13... Nf6 {[%clk 0:02:21]} 14. e4 {[%clk 0:02:31.4]} 14... dxe4 {[%clk 0:02:19.7]} 15. fxe4 {[%clk 0:02:30.8]} 15... Bb4 {[%clk 0:02:14.7]} 16. e5 {[%clk 0:02:27]} 16... Nd5 {[%clk 0:02:06.9]} 17. Nxd5 {[%clk 0:02:24.8]} 17... exd5 {[%clk 0:02:06.8]} 18. Rf3 {[%clk 0:02:21.8]} 18... Rfe8 {[%clk 0:01:59.6]} 19. Bf4 {[%clk 0:02:17]} 19... Rac8 {[%clk 0:01:50.6]} 20. c3 {[%clk 0:02:15]} 20... Ba5 {[%clk 0:01:49.3]} 21. b4 {[%clk 0:02:13.8]} 21... Bb6+ {[%clk 0:01:48]} 22. Kh1 {[%clk 0:02:12.4]} 22... h6 {[%clk 0:01:42.7]} 23. Rc1 {[%clk 0:02:09.1]} 23... Rc4 {[%clk 0:01:35.9]} 24. Rg3 {[%clk 0:02:06.6]} 24... Kh7 {[%clk 0:01:34.4]} 25. h4 {[%clk 0:02:02.1]} 25... Re6 {[%clk 0:01:27.6]} 26. Rd3 {[%clk 0:01:59.2]} 26... d4 {[%clk 0:01:23.9]} 27. cxd4 {[%clk 0:01:57.6]} 27... Rxd4 {[%clk 0:01:13.3]} 28. Rxd4 {[%clk 0:01:55.1]} 28... Bxd4 {[%clk 0:01:12.2]} 29. Rc7 {[%clk 0:01:46.9]} 29... Bxe5 {[%clk 0:01:09.8]} 30. Bxe5 {[%clk 0:01:46]} 30... Rxe5 {[%clk 0:01:08.6]} 31. Rxb7 {[%clk 0:01:44.8]} 31... Kg6 {[%clk 0:01:01.7]} 32. Rxa7 {[%clk 0:01:42.7]} 32... Re4 {[%clk 0:01:00]} 33. b5 {[%clk 0:01:41.6]} 33... Rxh4+ {[%clk 0:00:57.9]} 34. Kg1 {[%clk 0:01:40.3]} 34... Rb4 {[%clk 0:00:55.7]} 35. Rb7 {[%clk 0:01:37.4]} 35... Kf6 {[%clk 0:00:52.8]} 36. b6 {[%clk 0:01:36.4]} 36... Ke6 {[%clk 0:00:51.5]} 37. Kf2 {[%clk 0:01:34.6]} 37... Kd6 {[%clk 0:00:44.4]} 38. Rxf7 {[%clk 0:01:31.6]} 38... Rxb6 {[%clk 0:00:42.5]} 39. Rxg7 {[%clk 0:01:30.5]} 39... Kc5 {[%clk 0:00:40.3]} 40. Ra7 {[%clk 0:01:27.3]} 40... Rb2+ {[%clk 0:00:35.7]} 41. Kf3 {[%clk 0:01:25.9]} 41... Rb6 {[%clk 0:00:33.8]} 42. g4 {[%clk 0:01:24.8]} 42... Rf6+ {[%clk 0:00:30.9]} 43. Kg3 {[%clk 0:01:24]} 43... Kb6 {[%clk 0:00:26.2]} 44. Ra8 {[%clk 0:01:20]} 44... Rg6 {[%clk 0:00:23.9]} 45. Kh4 {[%clk 0:01:19.2]} 45... Rc6 {[%clk 0:00:20]} 46. Kh5 {[%clk 0:01:18.3]} 46... Kb5 {[%clk 0:00:18.8]} 47. a4+ {[%clk 0:01:15.1]} 47... Kb6 {[%clk 0:00:17.2]} 48. a5+ {[%clk 0:01:13.6]} 48... Kb7 {[%clk 0:00:15.3]} 49. Rh8 {[%clk 0:01:10.5]} 49... Ra6 {[%clk 0:00:13.4]} 50. Rxh6 {[%clk 0:01:08.6]} 50... Rxh6+ {[%clk 0:00:12.9]} 51. Kxh6 {[%clk 0:01:07.6]} 51... Ka6 {[%clk 0:00:12.8]} 52. g5 {[%clk 0:01:07.1]} 52... Kxa5 {[%clk 0:00:12.7]} 53. g6 {[%clk 0:01:06.8]} 1-0\n",
            "time_control": "180",
            "end_time": 1741393606,
            "rated": true,
            "tcn": "lBZJmu!Tgv6LftLtdt0SvKYIBI9IbsIRtH5ZKZ7ZHZTZeg8!nvZTuCJCvCRzCKTJsJSJfv98cD46kszGjzGPgh3Vac6Avw!3pF8SwtJBsBABtBPBcYBKDKSKYX3UXWKCzHCFhgFzWXUTHPTSgnSRX1zP12RI2WPjnvjPoEPTvwIPW4TUwFUQFNPHiyHPyGPX4?QO?VOVNVXOEMOGMU",
            "uuid": "50ce7570-fbb3-11ef-b347-fd9cae01000f",
            "initial_setup": "rnbqkbnr/pppppppp/8/8/8/8/PPPPPPPP/RNBQKBNR w KQkq - 0 1",
            "fen": "8/8/6PK/k7/8/8/8/8 b - -",
            "time_class": "blitz",
            "rules": "chess",
            "white": {
                "rating": 804,
                "result": "win",
                "@id": "https://api.chess.com/pub/player/th8577",
                "username": "TH8577",
                "uuid": "7b8c6122-6245-11ee-a0a5-eb7a92a84b49"
            },
            "black": {
                "rating": 807,
                "result": "resigned",
                "@id": "https://api.chess.com/pub/player/jorgepr1",
                "username": "Jorgepr1",
                "uuid": "22e90e32-1d95-11eb-989c-891235857dcd"
            },
            "eco": "https://www.chess.com/openings/Colle-System-Anti-Colle-Variation-4.Bd3-Bxd3-5.Qxd3"
        },
        {
            "url": "https://www.chess.com/game/live/136022458756",
            "pgn": "[Event \"Live Chess\"]\n[Site \"Chess.com\"]\n[Date \"2025.03.08\"]\n[Round \"-\"]\n[White \"jburt45\"]\n[Black \"Jorgepr1\"]\n[Result \"0-1\"]\n[CurrentPosition \"8/1p6/8/2Rp2p1/bP1P1k2/5P2/4K3/2qr4 w - -\"]\n[Timezone \"UTC\"]\n[ECO \"D02\"]\n[ECOUrl \"https://www.chess.com/openings/London-System-3...Bf5-4.e3-e6\"]\n[UTCDate \"2025.03.08\"]\n[UTCTime \"00:26:50\"]\n[WhiteElo \"800\"]\n[BlackElo \"815\"]\n[TimeControl \"180\"]\n[Termination \"Jorgepr1 won on time\"]\n[StartTime \"00:26:50\"]\n[EndDate \"2025.03.08\"]\n[EndTime \"00:32:50\"]\n[Link \"https://www.chess.com/game/live/136022458756\"]\n\n1. d4 {[%clk 0:02:52.7]} 1... d5 {[%clk 0:02:59.2]} 2. Bf4 {[%clk 0:02:51.3]} 2... Nf6 {[%clk 0:02:56.7]} 3. Nf3 {[%clk 0:02:51.1]} 3... Bf5 {[%clk 0:02:54.8]} 4. e3 {[%clk 0:02:51]} 4... e6 {[%clk 0:02:53.5]} 5. Nc3 {[%clk 0:02:48.6]} 5... c5 {[%clk 0:02:52.1]} 6. Bb5+ {[%clk 0:02:45.9]} 6... Nbd7 {[%clk 0:02:47.8]} 7. Ne5 {[%clk 0:02:44.6]} 7... a6 {[%clk 0:02:43.4]} 8. Bxd7+ {[%clk 0:02:42.8]} 8... Nxd7 {[%clk 0:02:41.3]} 9. Nxd7 {[%clk 0:02:38.4]} 9... Qxd7 {[%clk 0:02:41.2]} 10. O-O {[%clk 0:02:34.3]} 10... cxd4 {[%clk 0:02:36.6]} 11. Qxd4 {[%clk 0:02:23.5]} 11... Qc6 {[%clk 0:02:32.7]} 12. Rac1 {[%clk 0:02:04.7]} 12... Bc5 {[%clk 0:02:28.8]} 13. Qd2 {[%clk 0:01:59.3]} 13... O-O {[%clk 0:02:25.5]} 14. b3 {[%clk 0:01:51.5]} 14... Bb4 {[%clk 0:02:22.3]} 15. Be5 {[%clk 0:01:43.7]} 15... f6 {[%clk 0:02:21]} 16. Bd4 {[%clk 0:01:31.4]} 16... e5 {[%clk 0:02:17.9]} 17. a3 {[%clk 0:01:26.8]} 17... exd4 {[%clk 0:02:11]} 18. axb4 {[%clk 0:01:22.6]} 18... dxc3 {[%clk 0:02:07.8]} 19. Qd4 {[%clk 0:01:20.8]} 19... Bg6 {[%clk 0:01:55.9]} 20. h3 {[%clk 0:01:18.2]} 20... Rfe8 {[%clk 0:01:52.1]} 21. Rfe1 {[%clk 0:01:15.5]} 21... a5 {[%clk 0:01:48.3]} 22. Ra1 {[%clk 0:01:13.5]} 22... Bxc2 {[%clk 0:01:35.2]} 23. Rxa5 {[%clk 0:00:42.2]} 23... Bxb3 {[%clk 0:01:24.8]} 24. Rea1 {[%clk 0:00:39.2]} 24... Rxa5 {[%clk 0:01:12.8]} 25. Rxa5 {[%clk 0:00:36.6]} 25... Qc4 {[%clk 0:01:01.3]} 26. Rc5 {[%clk 0:00:36.5]} 26... Qxd4 {[%clk 0:00:54.5]} 27. exd4 {[%clk 0:00:34.7]} 27... c2 {[%clk 0:00:48.9]} 28. Rc3 {[%clk 0:00:33.4]} 28... Ba4 {[%clk 0:00:46.5]} 29. Kf1 {[%clk 0:00:30]} 29... Kf7 {[%clk 0:00:42.4]} 30. f3 {[%clk 0:00:21.2]} 30... g5 {[%clk 0:00:38.6]} 31. Kf2 {[%clk 0:00:20.2]} 31... Kg6 {[%clk 0:00:38.1]} 32. g4 {[%clk 0:00:18.8]} 32... h5 {[%clk 0:00:36.7]} 33. Kg3 {[%clk 0:00:18]} 33... hxg4 {[%clk 0:00:35.7]} 34. hxg4 {[%clk 0:00:16.7]} 34... f5 {[%clk 0:00:34.2]} 35. gxf5+ {[%clk 0:00:15.4]} 35... Kxf5 {[%clk 0:00:34.1]} 36. Kf2 {[%clk 0:00:13.3]} 36... Kf4 {[%clk 0:00:32.5]} 37. Kg2 {[%clk 0:00:11.7]} 37... Re3 {[%clk 0:00:27]} 38. Rc5 {[%clk 0:00:06.5]} 38... Re1 {[%clk 0:00:20.6]} 39. Kf2 {[%clk 0:00:04.2]} 39... Rd1 {[%clk 0:00:17.3]} 40. Ke2 {[%clk 0:00:02.6]} 40... c1=Q {[%clk 0:00:15.6]} 0-1\n",
            "time_control": "180",
            "end_time": 1741393970,
            "rated": true,
            "tcn": "lBZJcD!Tgv6Lmu0SbsYIfH5ZvKWOHZTZKZ7ZegIBdBZQac9IBl8!jrIzDK1TKBSKiqKBqzBslBLUpx98feOGcaUkaGkrea4GaGQAGIABuBskIsrygf!1nv2Mfn1UoE3NnwNExETLELULwnLDno8usIueonednmk~",
            "uuid": "073bf6a0-fbb4-11ef-98f2-8bcf2701000f",
            "initial_setup": "rnbqkbnr/pppppppp/8/8/8/8/PPPPPPPP/RNBQKBNR w KQkq - 0 1",
            "fen": "8/1p6/8/2Rp2p1/bP1P1k2/5P2/4K3/2qr4 w - -",
            "time_class": "blitz",
            "rules": "chess",
            "white": {
                "rating": 800,
                "result": "timeout",
                "@id": "https://api.chess.com/pub/player/jburt45",
                "username": "jburt45",
                "uuid": "2b635260-0e39-11e4-8056-000000000000"
            },
            "black": {
                "rating": 815,
                "result": "win",
                "@id": "https://api.chess.com/pub/player/jorgepr1",
                "username": "Jorgepr1",
                "uuid": "22e90e32-1d95-11eb-989c-891235857dcd"
            },
            "eco": "https://www.chess.com/openings/London-System-3...Bf5-4.e3-e6"
        },
        {
            "url": "https://www.chess.com/game/live/136022575638",
            "pgn": "[Event \"Live Chess\"]\n[Site \"Chess.com\"]\n[Date \"2025.03.08\"]\n[Round \"-\"]\n[White \"Jorgepr1\"]\n[Black \"ceezarsc\"]\n[Result \"0-1\"]\n[CurrentPosition \"8/2Rprpkp/4pNp1/4P3/P2P4/2P1b2P/6P1/5q1K w - -\"]\n[Timezone \"UTC\"]\n[ECO \"B27\"]\n[ECOUrl \"https://www.chess.com/openings/Sicilian-Defense-Hyperaccelerated-Dragon-Variation-3.c3-Bg7-4.d4-cxd4-5.cxd4\"]\n[UTCDate \"2025.03.08\"]\n[UTCTime \"00:32:56\"]\n[WhiteElo \"807\"]\n[BlackElo \"814\"]\n[TimeControl \"180\"]\n[Termination \"ceezarsc won by resignation\"]\n[StartTime \"00:32:56\"]\n[EndDate \"2025.03.08\"]\n[EndTime \"00:38:01\"]\n[Link \"https://www.chess.com/game/live/136022575638\"]\n\n1. e4 {[%clk 0:02:59.9]} 1... c5 {[%clk 0:02:51.9]} 2. Nf3 {[%clk 0:02:57.4]} 2... g6 {[%clk 0:02:51.4]} 3. d4 {[%clk 0:02:56.1]} 3... Bg7 {[%clk 0:02:50.8]} 4. c3 {[%clk 0:02:53.7]} 4... cxd4 {[%clk 0:02:49]} 5. cxd4 {[%clk 0:02:52.4]} 5... Nf6 {[%clk 0:02:48]} 6. e5 {[%clk 0:02:51]} 6... Ne4 {[%clk 0:02:46.7]} 7. Nc3 {[%clk 0:02:49.3]} 7... Nxc3 {[%clk 0:02:45.2]} 8. bxc3 {[%clk 0:02:49.2]} 8... O-O {[%clk 0:02:43.5]} 9. Qb3 {[%clk 0:02:47.3]} 9... e6 {[%clk 0:02:41.5]} 10. Bd3 {[%clk 0:02:42.1]} 10... Nc6 {[%clk 0:02:38.5]} 11. O-O {[%clk 0:02:39.3]} 11... Na5 {[%clk 0:02:37.4]} 12. Qa4 {[%clk 0:02:22.9]} 12... b6 {[%clk 0:02:35]} 13. Bb2 {[%clk 0:02:07.5]} 13... Bb7 {[%clk 0:02:33.5]} 14. Qc2 {[%clk 0:02:04.7]} 14... Qc7 {[%clk 0:02:31.6]} 15. Be4 {[%clk 0:02:02.4]} 15... Ba6 {[%clk 0:02:27.2]} 16. Rfe1 {[%clk 0:02:00.7]} 16... Rac8 {[%clk 0:02:25.2]} 17. Ba3 {[%clk 0:01:51.6]} 17... Rfe8 {[%clk 0:02:19.9]} 18. Bd6 {[%clk 0:01:50.6]} 18... Qd8 {[%clk 0:02:06.4]} 19. Bd3 {[%clk 0:01:32.7]} 19... Nc6 {[%clk 0:02:03.9]} 20. Bxa6 {[%clk 0:01:27]} 20... b5 {[%clk 0:01:56.7]} 21. Bxc8 {[%clk 0:01:24.2]} 21... Qxc8 {[%clk 0:01:55.5]} 22. Rab1 {[%clk 0:01:16.7]} 22... a5 {[%clk 0:01:54.7]} 23. Rxb5 {[%clk 0:01:14.2]} 23... Qa6 {[%clk 0:01:54.3]} 24. a4 {[%clk 0:00:57.8]} 24... Bh6 {[%clk 0:01:49.9]} 25. Nd2 {[%clk 0:00:48.2]} 25... Ne7 {[%clk 0:01:47.5]} 26. Bxe7 {[%clk 0:00:33.6]} 26... Rxe7 {[%clk 0:01:45.7]} 27. Ne4 {[%clk 0:00:33]} 27... Qc6 {[%clk 0:01:42.4]} 28. Nf6+ {[%clk 0:00:29.1]} 28... Kg7 {[%clk 0:01:40.7]} 29. h3 {[%clk 0:00:19.3]} 29... Qc4 {[%clk 0:01:38.8]} 30. Qb3 {[%clk 0:00:15.7]} 30... Qd3 {[%clk 0:01:37]} 31. Rxa5 {[%clk 0:00:13.6]} 31... Bd2 {[%clk 0:01:30.2]} 32. Rc5 {[%clk 0:00:12.4]} 32... Bxe1 {[%clk 0:01:29]} 33. Kh2 {[%clk 0:00:12]} 33... Bxf2 {[%clk 0:01:27.3]} 34. Qb1 {[%clk 0:00:10.1]} 34... Qg3+ {[%clk 0:01:24.8]} 35. Kh1 {[%clk 0:00:07.7]} 35... Be3 {[%clk 0:01:21.4]} 36. Qf1 {[%clk 0:00:05.8]} 36... Qf2 {[%clk 0:01:18.6]} 37. Rc7 {[%clk 0:00:04]} 37... Qxf1+ {[%clk 0:01:15.8]} 0-1\n",
            "time_control": "180",
            "end_time": 1741394281,
            "rated": true,
            "tcn": "mCYIgv2UlB92ksIBsB!TCKTCbsCsjs8!dr0Sft5QegQGryXPcj6Xyk7YtCXOfe46jq98qRY7CtGQtOPHO676abWGbH6Oiy2VvlQ0R080lCOQCT!2pxQAkrAtHGVlGIlegpenrbtwphnubfwnIYnf",
            "uuid": "e1324e4b-fbb4-11ef-b347-fd9cae01000f",
            "initial_setup": "rnbqkbnr/pppppppp/8/8/8/8/PPPPPPPP/RNBQKBNR w KQkq - 0 1",
            "fen": "8/2Rprpkp/4pNp1/4P3/P2P4/2P1b2P/6P1/5q1K w - -",
            "time_class": "blitz",
            "rules": "chess",
            "white": {
                "rating": 807,
                "result": "resigned",
                "@id": "https://api.chess.com/pub/player/jorgepr1",
                "username": "Jorgepr1",
                "uuid": "22e90e32-1d95-11eb-989c-891235857dcd"
            },
            "black": {
                "rating": 814,
                "result": "win",
                "@id": "https://api.chess.com/pub/player/ceezarsc",
                "username": "ceezarsc",
                "uuid": "82e9de86-aea2-11ef-ad23-afeec53a43ac"
            },
            "eco": "https://www.chess.com/openings/Sicilian-Defense-Hyperaccelerated-Dragon-Variation-3.c3-Bg7-4.d4-cxd4-5.cxd4"
        },
        {
            "url": "https://www.chess.com/game/live/136022673850",
            "pgn": "[Event \"Live Chess\"]\n[Site \"Chess.com\"]\n[Date \"2025.03.08\"]\n[Round \"-\"]\n[White \"Jorgepr1\"]\n[Black \"PreciseOne9080\"]\n[Result \"1-0\"]\n[CurrentPosition \"r3r1k1/4bp2/p1Nq1n1p/5bp1/8/2NP2B1/1PPQ1PPP/R3R1K1 w - -\"]\n[Timezone \"UTC\"]\n[ECO \"B02\"]\n[ECOUrl \"https://www.chess.com/openings/Alekhines-Defense-Scandinavian-Variation-3.exd5\"]\n[UTCDate \"2025.03.08\"]\n[UTCTime \"00:38:05\"]\n[WhiteElo \"815\"]\n[BlackElo \"804\"]\n[TimeControl \"180\"]\n[Termination \"Jorgepr1 won by resignation\"]\n[StartTime \"00:38:05\"]\n[EndDate \"2025.03.08\"]\n[EndTime \"00:41:34\"]\n[Link \"https://www.chess.com/game/live/136022673850\"]\n\n1. e4 {[%clk 0:02:58.8]} 1... d5 {[%clk 0:02:59.8]} 2. exd5 {[%clk 0:02:57.5]} 2... Nf6 {[%clk 0:02:58.2]} 3. Nc3 {[%clk 0:02:55.5]} 3... Bf5 {[%clk 0:02:56.1]} 4. Nf3 {[%clk 0:02:53.3]} 4... Qd7 {[%clk 0:02:48.8]} 5. Bc4 {[%clk 0:02:50.2]} 5... c6 {[%clk 0:02:46.1]} 6. dxc6 {[%clk 0:02:47]} 6... Nxc6 {[%clk 0:02:45.1]} 7. d3 {[%clk 0:02:44.3]} 7... e5 {[%clk 0:02:43.5]} 8. Bg5 {[%clk 0:02:39.7]} 8... Be7 {[%clk 0:02:40.9]} 9. O-O {[%clk 0:02:38.4]} 9... O-O {[%clk 0:02:39.4]} 10. Bb5 {[%clk 0:02:35.2]} 10... a6 {[%clk 0:02:36.7]} 11. Bxc6 {[%clk 0:02:29.4]} 11... Qxc6 {[%clk 0:02:35.4]} 12. Nxe5 {[%clk 0:02:27.2]} 12... Qd6 {[%clk 0:02:16.6]} 13. Nf3 {[%clk 0:02:21.3]} 13... Rfe8 {[%clk 0:02:06.6]} 14. Re1 {[%clk 0:02:19.6]} 14... h6 {[%clk 0:02:02.4]} 15. Bh4 {[%clk 0:02:17.1]} 15... g5 {[%clk 0:01:59.6]} 16. Bg3 {[%clk 0:02:04.3]} 16... Qd7 {[%clk 0:01:57.6]} 17. Qd2 {[%clk 0:01:55.6]} 17... b5 {[%clk 0:01:47.9]} 18. Ne5 {[%clk 0:01:52]} 18... Qb7 {[%clk 0:01:34.6]} 19. a3 {[%clk 0:01:38.5]} 19... b4 {[%clk 0:01:27.4]} 20. axb4 {[%clk 0:01:37]} 20... Qxb4 {[%clk 0:01:26.4]} 21. Nc6 {[%clk 0:01:25.5]} 21... Qd6 {[%clk 0:01:21.7]} 1-0\n",
            "time_control": "180",
            "end_time": 1741394494,
            "rated": true,
            "tcn": "mCZJCJ!Tbs6Lgv7ZfAYQJQ5Qlt0KcM90eg8!AHWOHQZQvKQRKv98fe3VMF2MFwRZdlXHvKZXiqHzqzXzKQzR",
            "uuid": "99c40f3a-fbb5-11ef-b347-fd9cae01000f",
            "initial_setup": "rnbqkbnr/pppppppp/8/8/8/8/PPPPPPPP/RNBQKBNR w KQkq - 0 1",
            "fen": "r3r1k1/4bp2/p1Nq1n1p/5bp1/8/2NP2B1/1PPQ1PPP/R3R1K1 w - -",
            "time_class": "blitz",
            "rules": "chess",
            "white": {
                "rating": 815,
                "result": "win",
                "@id": "https://api.chess.com/pub/player/jorgepr1",
                "username": "Jorgepr1",
                "uuid": "22e90e32-1d95-11eb-989c-891235857dcd"
            },
            "black": {
                "rating": 804,
                "result": "resigned",
                "@id": "https://api.chess.com/pub/player/preciseone9080",
                "username": "PreciseOne9080",
                "uuid": "e4b644b0-7a56-11ed-9046-5fa9d26f8c82"
            },
            "eco": "https://www.chess.com/openings/Alekhines-Defense-Scandinavian-Variation-3.exd5"
        },
        {
            "url": "https://www.chess.com/game/live/136026989672",
            "pgn": "[Event \"Live Chess\"]\n[Site \"Chess.com\"]\n[Date \"2025.03.08\"]\n[Round \"-\"]\n[White \"Forgul\"]\n[Black \"Jorgepr1\"]\n[Result \"1-0\"]\n[CurrentPosition \"8/kp2r3/p2p1r1p/3K4/8/P3R2P/8/8 b - -\"]\n[Timezone \"UTC\"]\n[ECO \"C44\"]\n[ECOUrl \"https://www.chess.com/openings/Kings-Pawn-Opening-Kings-Knight-Variation-2...Nc6-3.d3\"]\n[UTCDate \"2025.03.08\"]\n[UTCTime \"04:36:03\"]\n[WhiteElo \"821\"]\n[BlackElo \"807\"]\n[TimeControl \"180\"]\n[Termination \"Forgul won on time\"]\n[StartTime \"04:36:03\"]\n[EndDate \"2025.03.08\"]\n[EndTime \"04:42:16\"]\n[Link \"https://www.chess.com/game/live/136026989672\"]\n\n1. e4 {[%clk 0:02:59.8]} 1... e5 {[%clk 0:02:59.5]} 2. Nf3 {[%clk 0:02:59.6]} 2... Nc6 {[%clk 0:02:58.9]} 3. d3 {[%clk 0:02:58.4]} 3... Bc5 {[%clk 0:02:58.3]} 4. Nc3 {[%clk 0:02:56.9]} 4... d6 {[%clk 0:02:57.7]} 5. Be2 {[%clk 0:02:53.9]} 5... Nf6 {[%clk 0:02:56.9]} 6. O-O {[%clk 0:02:53.3]} 6... Bg4 {[%clk 0:02:56]} 7. h3 {[%clk 0:02:51.3]} 7... Bh5 {[%clk 0:02:53.7]} 8. g4 {[%clk 0:02:49.9]} 8... Bg6 {[%clk 0:02:51.3]} 9. Nh2 {[%clk 0:02:43.6]} 9... Qd7 {[%clk 0:02:48.3]} 10. Nd5 {[%clk 0:02:34.9]} 10... Nxd5 {[%clk 0:02:45]} 11. exd5 {[%clk 0:02:34.8]} 11... Nd4 {[%clk 0:02:42.4]} 12. c3 {[%clk 0:02:30.9]} 12... Nxe2+ {[%clk 0:02:35.9]} 13. Qxe2 {[%clk 0:02:30.8]} 13... O-O-O {[%clk 0:02:34.3]} 14. Bg5 {[%clk 0:02:21.9]} 14... f6 {[%clk 0:02:29.8]} 15. Bh4 {[%clk 0:02:19.3]} 15... c6 {[%clk 0:02:16.4]} 16. dxc6 {[%clk 0:02:17.4]} 16... Qxc6 {[%clk 0:02:16.3]} 17. d4 {[%clk 0:02:16.5]} 17... exd4 {[%clk 0:02:14.7]} 18. cxd4 {[%clk 0:02:16.4]} 18... Bxd4 {[%clk 0:02:11.9]} 19. g5 {[%clk 0:02:12.8]} 19... Bxb2 {[%clk 0:01:56.9]} 20. Rab1 {[%clk 0:02:02.5]} 20... Bxb1 {[%clk 0:01:53.9]} 21. Rxb1 {[%clk 0:02:00]} 21... Bd4 {[%clk 0:01:40.1]} 22. Nf3 {[%clk 0:01:48.1]} 22... Bc5 {[%clk 0:01:33.9]} 23. Rc1 {[%clk 0:01:41.7]} 23... fxg5 {[%clk 0:01:31.5]} 24. Bxg5 {[%clk 0:01:39.3]} 24... Rde8 {[%clk 0:01:30.1]} 25. Qd2 {[%clk 0:01:27.7]} 25... Kb8 {[%clk 0:01:27.7]} 26. Nd4 {[%clk 0:01:22]} 26... Qd5 {[%clk 0:01:14.2]} 27. Nb5 {[%clk 0:01:16]} 27... Qxd2 {[%clk 0:01:03.8]} 28. Bxd2 {[%clk 0:01:15.8]} 28... a6 {[%clk 0:00:54.5]} 29. Nc3 {[%clk 0:01:09.3]} 29... Bb4 {[%clk 0:00:49.4]} 30. Nb1 {[%clk 0:01:02.9]} 30... Bxd2 {[%clk 0:00:48.4]} 31. Nxd2 {[%clk 0:01:02.8]} 31... Re2 {[%clk 0:00:39.8]} 32. Rc2 {[%clk 0:00:55.7]} 32... Rc8 {[%clk 0:00:34.4]} 33. Rb2 {[%clk 0:00:52.5]} 33... Kc7 {[%clk 0:00:27.5]} 34. Kf1 {[%clk 0:00:47.8]} 34... Re6 {[%clk 0:00:19.2]} 35. Rc2+ {[%clk 0:00:41.3]} 35... Kb8 {[%clk 0:00:17.5]} 36. Rb2 {[%clk 0:00:36.9]} 36... Ka7 {[%clk 0:00:16.4]} 37. Nf3 {[%clk 0:00:35]} 37... Re7 {[%clk 0:00:15.4]} 38. Ng5 {[%clk 0:00:33.2]} 38... h6 {[%clk 0:00:12.8]} 39. Nf3 {[%clk 0:00:30.4]} 39... Rd7 {[%clk 0:00:12.3]} 40. Re2 {[%clk 0:00:27.5]} 40... Rc5 {[%clk 0:00:11.2]} 41. Re6 {[%clk 0:00:26.2]} 41... Rf5 {[%clk 0:00:10.5]} 42. Re3 {[%clk 0:00:23.6]} 42... Kb6 {[%clk 0:00:09.8]} 43. Nd4 {[%clk 0:00:21.6]} 43... Rd5 {[%clk 0:00:07.8]} 44. Ne6 {[%clk 0:00:20.4]} 44... Ka7 {[%clk 0:00:06.4]} 45. Nxg7 {[%clk 0:00:19.4]} 45... Rxg7 {[%clk 0:00:04.8]} 46. f4 {[%clk 0:00:17.6]} 46... Rh7 {[%clk 0:00:04.3]} 47. Kf2 {[%clk 0:00:17.5]} 47... Rd4 {[%clk 0:00:03.6]} 48. Kf3 {[%clk 0:00:17.4]} 48... Ra4 {[%clk 0:00:03.2]} 49. a3 {[%clk 0:00:15.2]} 49... Rc4 {[%clk 0:00:01.7]} 50. f5 {[%clk 0:00:14.4]} 50... Rc1 {[%clk 0:00:01.6]} 51. f6 {[%clk 0:00:14.2]} 51... Rf1+ {[%clk 0:00:00.7]} 52. Ke4 {[%clk 0:00:13.2]} 52... Rxf6 {[%clk 0:00:00.6]} 53. Kd4 {[%clk 0:00:12.8]} 53... Re7 {[%clk 0:00:00.1]} 54. Kd5 {[%clk 0:00:12.2]} 1-0\n",
            "time_control": "180",
            "end_time": 1741408936,
            "rated": true,
            "tcn": "mC0Kgv5Qlt9IbsZRfm!Teg6EpxENoENUvp7ZsJTJCJQBksBmdm86cM1TMFYQJQZQtBKBsBIBEMBjabUbfbjBpvBIbcTMFM78ml65vBQJBHJlMlWOHsIzsbzlbl8mck?6kj5YgfmSjkY5kj5WlvS0vM3VMv0Zjm6ImSILSuWPvBLJBSPWS2Z2nD23fnJBnvByiqyADLAcLTcfvCfTCB30BJ",
            "uuid": "d80b7fc8-fbd6-11ef-b347-fd9cae01000f",
            "initial_setup": "rnbqkbnr/pppppppp/8/8/8/8/PPPPPPPP/RNBQKBNR w KQkq - 0 1",
            "fen": "8/kp2r3/p2p1r1p/3K4/8/P3R2P/8/8 b - -",
            "time_class": "blitz",
            "rules": "chess",
            "white": {
                "rating": 821,
                "result": "win",
                "@id": "https://api.chess.com/pub/player/forgul",
                "username": "Forgul",
                "uuid": "60e75b38-51ae-11eb-b8d8-6d6b22d52103"
            },
            "black": {
                "rating": 807,
                "result": "timeout",
                "@id": "https://api.chess.com/pub/player/jorgepr1",
                "username": "Jorgepr1",
                "uuid": "22e90e32-1d95-11eb-989c-891235857dcd"
            },
            "eco": "https://www.chess.com/openings/Kings-Pawn-Opening-Kings-Knight-Variation-2...Nc6-3.d3"
        },
        {
            "url": "https://www.chess.com/game/live/136027109658",
            "pgn": "[Event \"Live Chess\"]\n[Site \"Chess.com\"]\n[Date \"2025.03.08\"]\n[Round \"-\"]\n[White \"westerly65\"]\n[Black \"Jorgepr1\"]\n[Result \"1-0\"]\n[CurrentPosition \"1k1Q1b1r/ppp1Npp1/7p/4n2b/1PB5/P4N1P/5PP1/R3K2R b KQ -\"]\n[Timezone \"UTC\"]\n[ECO \"D06\"]\n[ECOUrl \"https://www.chess.com/openings/Queens-Gambit-Declined-Baltic-Defense-3.Nf3\"]\n[UTCDate \"2025.03.08\"]\n[UTCTime \"04:42:38\"]\n[WhiteElo \"838\"]\n[BlackElo \"800\"]\n[TimeControl \"180\"]\n[Termination \"westerly65 won by checkmate\"]\n[StartTime \"04:42:38\"]\n[EndDate \"2025.03.08\"]\n[EndTime \"04:44:22\"]\n[Link \"https://www.chess.com/game/live/136027109658\"]\n\n1. d4 {[%clk 0:02:59]} 1... d5 {[%clk 0:02:57.3]} 2. Nf3 {[%clk 0:02:58.7]} 2... Bf5 {[%clk 0:02:53.3]} 3. c4 {[%clk 0:02:58.1]} 3... dxc4 {[%clk 0:02:51.6]} 4. Nc3 {[%clk 0:02:57.7]} 4... Nf6 {[%clk 0:02:50]} 5. h3 {[%clk 0:02:57.2]} 5... e6 {[%clk 0:02:49.2]} 6. Bg5 {[%clk 0:02:53.1]} 6... Nc6 {[%clk 0:02:47.2]} 7. e4 {[%clk 0:02:49]} 7... Bg6 {[%clk 0:02:43.5]} 8. a3 {[%clk 0:02:39]} 8... h6 {[%clk 0:02:41.8]} 9. Bxf6 {[%clk 0:02:37.4]} 9... Qxf6 {[%clk 0:02:39.4]} 10. e5 {[%clk 0:02:34.1]} 10... Qe7 {[%clk 0:02:32.2]} 11. Bxc4 {[%clk 0:02:32.8]} 11... O-O-O {[%clk 0:02:30.3]} 12. b4 {[%clk 0:02:29.2]} 12... Bh5 {[%clk 0:02:28.9]} 13. d5 {[%clk 0:02:17.8]} 13... exd5 {[%clk 0:02:25.4]} 14. Nxd5 {[%clk 0:02:12.4]} 14... Nxe5 {[%clk 0:02:22]} 15. Nxe7+ {[%clk 0:02:09.5]} 15... Kb8 {[%clk 0:02:19.2]} 16. Qxd8# {[%clk 0:02:02.6]} 1-0\n",
            "time_control": "180",
            "end_time": 1741409062,
            "rated": true,
            "tcn": "lBZJgv6LkAJAbs!Tpx0ScM5QmCLUiq3VMT7TCKT0fA86jzUNBJSJsJQKJ065d7",
            "uuid": "c34cdf4d-fbd7-11ef-bcba-e30dac01000f",
            "initial_setup": "rnbqkbnr/pppppppp/8/8/8/8/PPPPPPPP/RNBQKBNR w KQkq - 0 1",
            "fen": "1k1Q1b1r/ppp1Npp1/7p/4n2b/1PB5/P4N1P/5PP1/R3K2R b KQ -",
            "time_class": "blitz",
            "rules": "chess",
            "white": {
                "rating": 838,
                "result": "win",
                "@id": "https://api.chess.com/pub/player/westerly65",
                "username": "westerly65",
                "uuid": "1881a60c-8571-11ed-9611-d91075bdbc56"
            },
            "black": {
                "rating": 800,
                "result": "checkmated",
                "@id": "https://api.chess.com/pub/player/jorgepr1",
                "username": "Jorgepr1",
                "uuid": "22e90e32-1d95-11eb-989c-891235857dcd"
            },
            "eco": "https://www.chess.com/openings/Queens-Gambit-Declined-Baltic-Defense-3.Nf3"
        },
        {
            "url": "https://www.chess.com/game/live/136043864410",
            "pgn": "[Event \"Live Chess\"]\n[Site \"Chess.com\"]\n[Date \"2025.03.08\"]\n[Round \"-\"]\n[White \"Jorgepr1\"]\n[Black \"gpkanders\"]\n[Result \"1-0\"]\n[CurrentPosition \"r4r2/pppk2p1/2p1p3/8/4P3/2NP3Q/PPP3P1/2R3K1 b - -\"]\n[Timezone \"UTC\"]\n[ECO \"C42\"]\n[ECOUrl \"https://www.chess.com/openings/Petrovs-Defense-Classical-Variation\"]\n[UTCDate \"2025.03.08\"]\n[UTCTime \"15:57:10\"]\n[WhiteElo \"897\"]\n[BlackElo \"895\"]\n[TimeControl \"60\"]\n[Termination \"Jorgepr1 won on time\"]\n[StartTime \"15:57:10\"]\n[EndDate \"2025.03.08\"]\n[EndTime \"15:59:07\"]\n[Link \"https://www.chess.com/game/live/136043864410\"]\n\n1. e4 {[%clk 0:00:59.2]} 1... e5 {[%clk 0:00:59.1]} 2. Nf3 {[%clk 0:00:58.9]} 2... Nf6 {[%clk 0:00:58.7]} 3. Nxe5 {[%clk 0:00:57.4]} 3... Nc6 {[%clk 0:00:57.3]} 4. Nxc6 {[%clk 0:00:56.1]} 4... dxc6 {[%clk 0:00:57.2]} 5. Nc3 {[%clk 0:00:55.4]} 5... Bc5 {[%clk 0:00:56.9]} 6. Bc4 {[%clk 0:00:53.5]} 6... Ng4 {[%clk 0:00:55.9]} 7. O-O {[%clk 0:00:51.2]} 7... Qh4 {[%clk 0:00:55.6]} 8. h3 {[%clk 0:00:48.8]} 8... h5 {[%clk 0:00:55.2]} 9. Qf3 {[%clk 0:00:44.4]} 9... Be6 {[%clk 0:00:52.3]} 10. Bxe6 {[%clk 0:00:42.5]} 10... fxe6 {[%clk 0:00:52.2]} 11. d3 {[%clk 0:00:40.7]} 11... Rf8 {[%clk 0:00:37.8]} 12. Qg3 {[%clk 0:00:33.7]} 12... Nxf2 {[%clk 0:00:26.1]} 13. Qxh4 {[%clk 0:00:28.7]} 13... Nxh3+ {[%clk 0:00:24.4]} 14. Kh2 {[%clk 0:00:24.8]} 14... Nf4 {[%clk 0:00:23.5]} 15. Rxf4 {[%clk 0:00:20.1]} 15... Bd6 {[%clk 0:00:23.4]} 16. Qxh5+ {[%clk 0:00:18.6]} 16... Kd7 {[%clk 0:00:21.8]} 17. Kg1 {[%clk 0:00:12.7]} 17... Bxf4 {[%clk 0:00:20.9]} 18. Qh3 {[%clk 0:00:11.4]} 18... Bxc1 {[%clk 0:00:17.7]} 19. Rxc1 {[%clk 0:00:11]} 1-0\n",
            "time_control": "60",
            "end_time": 1741449547,
            "rated": true,
            "tcn": "mC0Kgv!TvK5QKQZQbs9IfATEeg7Fpx3Ndv6SAS1Slt?9vwEnwFnxgpxDfDIRFN8ZpgRDNxDcac",
            "uuid": "febead74-fc35-11ef-8c97-9c00a101000f",
            "initial_setup": "rnbqkbnr/pppppppp/8/8/8/8/PPPPPPPP/RNBQKBNR w KQkq - 0 1",
            "fen": "r4r2/pppk2p1/2p1p3/8/4P3/2NP3Q/PPP3P1/2R3K1 b - -",
            "time_class": "bullet",
            "rules": "chess",
            "white": {
                "rating": 897,
                "result": "win",
                "@id": "https://api.chess.com/pub/player/jorgepr1",
                "username": "Jorgepr1",
                "uuid": "22e90e32-1d95-11eb-989c-891235857dcd"
            },
            "black": {
                "rating": 895,
                "result": "timeout",
                "@id": "https://api.chess.com/pub/player/gpkanders",
                "username": "gpkanders",
                "uuid": "78fe6ce0-01e4-11ea-a45c-21da6ca5b9c8"
            },
            "eco": "https://www.chess.com/openings/Petrovs-Defense-Classical-Variation"
        },
        {
            "url": "https://www.chess.com/game/live/136043931126",
            "pgn": "[Event \"Live Chess\"]\n[Site \"Chess.com\"]\n[Date \"2025.03.08\"]\n[Round \"-\"]\n[White \"sinigangwithhodtog\"]\n[Black \"Jorgepr1\"]\n[Result \"1-0\"]\n[CurrentPosition \"8/8/Bp5p/p1p5/1kP3K1/6P1/8/8 b - -\"]\n[Timezone \"UTC\"]\n[ECO \"C50\"]\n[ECOUrl \"https://www.chess.com/openings/Giuoco-Piano-Game\"]\n[UTCDate \"2025.03.08\"]\n[UTCTime \"15:59:17\"]\n[WhiteElo \"898\"]\n[BlackElo \"889\"]\n[TimeControl \"60\"]\n[Termination \"sinigangwithhodtog won on time\"]\n[StartTime \"15:59:17\"]\n[EndDate \"2025.03.08\"]\n[EndTime \"16:01:36\"]\n[Link \"https://www.chess.com/game/live/136043931126\"]\n\n1. e4 {[%clk 0:00:59.8]} 1... e5 {[%clk 0:00:59.2]} 2. Nf3 {[%clk 0:00:59.4]} 2... Nc6 {[%clk 0:00:58.8]} 3. Bc4 {[%clk 0:00:58.6]} 3... Bc5 {[%clk 0:00:56.1]} 4. Nxe5 {[%clk 0:00:57]} 4... Nxe5 {[%clk 0:00:54.8]} 5. d4 {[%clk 0:00:56.6]} 5... Bxd4 {[%clk 0:00:53.4]} 6. Qxd4 {[%clk 0:00:55.3]} 6... d6 {[%clk 0:00:52]} 7. Be2 {[%clk 0:00:50.5]} 7... Nf6 {[%clk 0:00:51.3]} 8. Bg5 {[%clk 0:00:48.1]} 8... O-O {[%clk 0:00:49.3]} 9. Nc3 {[%clk 0:00:44.9]} 9... h6 {[%clk 0:00:47.2]} 10. Bxf6 {[%clk 0:00:44]} 10... Qxf6 {[%clk 0:00:45.5]} 11. O-O {[%clk 0:00:43.8]} 11... Ng4 {[%clk 0:00:44]} 12. Qxf6 {[%clk 0:00:43.1]} 12... Nxf6 {[%clk 0:00:43.9]} 13. Nd5 {[%clk 0:00:42.2]} 13... Be6 {[%clk 0:00:42.9]} 14. Nxf6+ {[%clk 0:00:41.1]} 14... gxf6 {[%clk 0:00:42.8]} 15. c4 {[%clk 0:00:39.4]} 15... c5 {[%clk 0:00:40.2]} 16. f3 {[%clk 0:00:38.3]} 16... b6 {[%clk 0:00:39.6]} 17. Rfd1 {[%clk 0:00:37.4]} 17... Rad8 {[%clk 0:00:38.6]} 18. b3 {[%clk 0:00:36.5]} 18... Kh7 {[%clk 0:00:37.9]} 19. Rd3 {[%clk 0:00:35]} 19... a6 {[%clk 0:00:37.3]} 20. Rad1 {[%clk 0:00:34.4]} 20... Rfe8 {[%clk 0:00:31.3]} 21. Rxd6 {[%clk 0:00:33]} 21... Rxd6 {[%clk 0:00:30.8]} 22. Rxd6 {[%clk 0:00:32.8]} 22... Kg6 {[%clk 0:00:28.5]} 23. Kf2 {[%clk 0:00:29.8]} 23... Rb8 {[%clk 0:00:27.3]} 24. a4 {[%clk 0:00:28.8]} 24... f5 {[%clk 0:00:25.8]} 25. Rxe6+ {[%clk 0:00:28]} 25... Kg7 {[%clk 0:00:24.3]} 26. exf5 {[%clk 0:00:26.7]} 26... fxe6 {[%clk 0:00:23.3]} 27. fxe6 {[%clk 0:00:26.6]} 27... Kf6 {[%clk 0:00:22.5]} 28. f4 {[%clk 0:00:23.2]} 28... Kxe6 {[%clk 0:00:21.8]} 29. Bg4+ {[%clk 0:00:23.1]} 29... Kf6 {[%clk 0:00:20.4]} 30. Kf3 {[%clk 0:00:22.4]} 30... Rd8 {[%clk 0:00:18.2]} 31. Ke2 {[%clk 0:00:21.2]} 31... Rd4 {[%clk 0:00:16.6]} 32. Bf3 {[%clk 0:00:20]} 32... Rxf4 {[%clk 0:00:15.5]} 33. g3 {[%clk 0:00:19.9]} 33... Rf5 {[%clk 0:00:14]} 34. Bb7 {[%clk 0:00:19]} 34... a5 {[%clk 0:00:11.3]} 35. Bc6 {[%clk 0:00:17.2]} 35... Re5+ {[%clk 0:00:10.8]} 36. Kf3 {[%clk 0:00:16.3]} 36... Re6 {[%clk 0:00:10.3]} 37. Bd5 {[%clk 0:00:15]} 37... Re1 {[%clk 0:00:09.6]} 38. Be4 {[%clk 0:00:13.3]} 38... Rb1 {[%clk 0:00:09.2]} 39. Bc2 {[%clk 0:00:12.7]} 39... Rb2 {[%clk 0:00:07.9]} 40. Bd1 {[%clk 0:00:11.5]} 40... Rxh2 {[%clk 0:00:07]} 41. Kg4 {[%clk 0:00:10.1]} 41... Rb2 {[%clk 0:00:06.4]} 42. Bf3 {[%clk 0:00:08.6]} 42... Rb1 {[%clk 0:00:05.5]} 43. Bd5 {[%clk 0:00:08.5]} 43... Rxb3 {[%clk 0:00:05]} 44. Bf3 {[%clk 0:00:07.4]} 44... Ra3 {[%clk 0:00:04.6]} 45. Bc6 {[%clk 0:00:06.7]} 45... Rxa4 {[%clk 0:00:04.2]} 46. Bxa4 {[%clk 0:00:06.2]} 46... Ke5 {[%clk 0:00:02.1]} 47. Bb5 {[%clk 0:00:06.1]} 47... Kd4 {[%clk 0:00:01.8]} 48. Ba4 {[%clk 0:00:05.4]} 48... Kc3 {[%clk 0:00:01.4]} 49. Bb5 {[%clk 0:00:05.3]} 49... Kb4 {[%clk 0:00:00.1]} 50. Ba6 {[%clk 0:00:05.2]} 1-0\n",
            "time_control": "60",
            "end_time": 1741449696,
            "rated": true,
            "tcn": "mC0Kgv5QfA9IvKQKlBIBdBZRAm!TcM8!bs3VMT7TegKEBTETsJ6SJT2TkAYInvXPfd47jr!3dtWOad98tR7RdR3Ugn85iyTLRSU2CL1SLS2TvDTSmESTnv57vm7BEvBDowDLvXOGXQLKmvKSQJSeJCebCkbjkdjpvEpjdvjbvJbrJvrqvQqyQyTKyHKBHyBsyHszHO",
            "uuid": "4a71f38f-fc36-11ef-bcba-e30dac01000f",
            "initial_setup": "rnbqkbnr/pppppppp/8/8/8/8/PPPPPPPP/RNBQKBNR w KQkq - 0 1",
            "fen": "8/8/Bp5p/p1p5/1kP3K1/6P1/8/8 b - -",
            "time_class": "bullet",
            "rules": "chess",
            "white": {
                "rating": 898,
                "result": "win",
                "@id": "https://api.chess.com/pub/player/sinigangwithhodtog",
                "username": "sinigangwithhodtog",
                "uuid": "579787c0-d072-11ed-bee3-8fd09c5a0e08"
            },
            "black": {
                "rating": 889,
                "result": "timeout",
                "@id": "https://api.chess.com/pub/player/jorgepr1",
                "username": "Jorgepr1",
                "uuid": "22e90e32-1d95-11eb-989c-891235857dcd"
            },
            "eco": "https://www.chess.com/openings/Giuoco-Piano-Game"
        },
        {
            "url": "https://www.chess.com/game/live/136044011786",
            "pgn": "[Event \"Live Chess\"]\n[Site \"Chess.com\"]\n[Date \"2025.03.08\"]\n[Round \"-\"]\n[White \"Jorgepr1\"]\n[Black \"AmoneTheGreat\"]\n[Result \"0-1\"]\n[CurrentPosition \"8/5k2/4p3/p5KP/8/8/8/8 w - -\"]\n[Timezone \"UTC\"]\n[ECO \"B07\"]\n[ECOUrl \"https://www.chess.com/openings/Pirc-Defense-Modern-Defense-Geller-System-2...Nf6\"]\n[UTCDate \"2025.03.08\"]\n[UTCTime \"16:01:52\"]\n[WhiteElo \"881\"]\n[BlackElo \"889\"]\n[TimeControl \"60\"]\n[Termination \"AmoneTheGreat won on time\"]\n[StartTime \"16:01:52\"]\n[EndDate \"2025.03.08\"]\n[EndTime \"16:03:55\"]\n[Link \"https://www.chess.com/game/live/136044011786\"]\n\n1. e4 {[%clk 0:00:58.8]} 1... d6 {[%clk 0:00:58.9]} 2. Nf3 {[%clk 0:00:58.4]} 2... Nf6 {[%clk 0:00:58.6]} 3. d3 {[%clk 0:00:57.1]} 3... g6 {[%clk 0:00:58.2]} 4. Nc3 {[%clk 0:00:56.4]} 4... Bg7 {[%clk 0:00:57.8]} 5. Bg5 {[%clk 0:00:55.7]} 5... Bg4 {[%clk 0:00:56.8]} 6. h3 {[%clk 0:00:54]} 6... Bxf3 {[%clk 0:00:54.7]} 7. Qxf3 {[%clk 0:00:51.6]} 7... Nbd7 {[%clk 0:00:54.4]} 8. g3 {[%clk 0:00:48.7]} 8... c5 {[%clk 0:00:53.2]} 9. Bg2 {[%clk 0:00:47]} 9... O-O {[%clk 0:00:52.4]} 10. O-O-O {[%clk 0:00:46]} 10... Qc7 {[%clk 0:00:51.4]} 11. Nd5 {[%clk 0:00:41.1]} 11... Qc6 {[%clk 0:00:49.7]} 12. Nxf6+ {[%clk 0:00:39.1]} 12... Bxf6 {[%clk 0:00:48.3]} 13. Bxf6 {[%clk 0:00:38.4]} 13... Nxf6 {[%clk 0:00:47.2]} 14. e5 {[%clk 0:00:35.2]} 14... dxe5 {[%clk 0:00:46.1]} 15. Qxc6 {[%clk 0:00:33.8]} 15... bxc6 {[%clk 0:00:45.9]} 16. Bxc6 {[%clk 0:00:32.5]} 16... Rab8 {[%clk 0:00:45.3]} 17. Be4 {[%clk 0:00:30.1]} 17... Nxe4 {[%clk 0:00:43.5]} 18. dxe4 {[%clk 0:00:29.9]} 18... Rfd8 {[%clk 0:00:42.7]} 19. Rxd8+ {[%clk 0:00:26.7]} 19... Rxd8 {[%clk 0:00:42.6]} 20. Rd1 {[%clk 0:00:25.2]} 20... Rd4 {[%clk 0:00:41.9]} 21. f3 {[%clk 0:00:23.1]} 21... Rxd1+ {[%clk 0:00:39.9]} 22. Kxd1 {[%clk 0:00:22.1]} 22... Kg7 {[%clk 0:00:39.5]} 23. Ke2 {[%clk 0:00:21.2]} 23... Kf6 {[%clk 0:00:39]} 24. Kd3 {[%clk 0:00:20.6]} 24... Ke6 {[%clk 0:00:38.5]} 25. c4 {[%clk 0:00:18.1]} 25... Kd6 {[%clk 0:00:37.9]} 26. a3 {[%clk 0:00:16.1]} 26... e6 {[%clk 0:00:35.7]} 27. b4 {[%clk 0:00:15.4]} 27... cxb4 {[%clk 0:00:34.7]} 28. axb4 {[%clk 0:00:15.3]} 28... Kc6 {[%clk 0:00:33.5]} 29. Kc3 {[%clk 0:00:14.9]} 29... h5 {[%clk 0:00:31.4]} 30. b5+ {[%clk 0:00:14.3]} 30... Kc5 {[%clk 0:00:30]} 31. Kb3 {[%clk 0:00:13.6]} 31... f6 {[%clk 0:00:28.7]} 32. h4 {[%clk 0:00:12.5]} 32... f5 {[%clk 0:00:27.3]} 33. exf5 {[%clk 0:00:11.3]} 33... gxf5 {[%clk 0:00:26.7]} 34. Kc3 {[%clk 0:00:10.2]} 34... e4 {[%clk 0:00:22.8]} 35. fxe4 {[%clk 0:00:09.1]} 35... fxe4 {[%clk 0:00:22.2]} 36. Kb3 {[%clk 0:00:07.6]} 36... e3 {[%clk 0:00:21.6]} 37. Kc3 {[%clk 0:00:07.2]} 37... e2 {[%clk 0:00:21.1]} 38. Kd2 {[%clk 0:00:06.4]} 38... e1=Q+ {[%clk 0:00:18.6]} 39. Kxe1 {[%clk 0:00:05.6]} 39... Kxc4 {[%clk 0:00:18.4]} 40. Ke2 {[%clk 0:00:05]} 40... Kxb5 {[%clk 0:00:18]} 41. Ke3 {[%clk 0:00:04.6]} 41... a5 {[%clk 0:00:16.2]} 42. Kf4 {[%clk 0:00:03.4]} 42... Kc6 {[%clk 0:00:15.5]} 43. g4 {[%clk 0:00:03.3]} 43... hxg4 {[%clk 0:00:13.7]} 44. Kxg4 {[%clk 0:00:02.2]} 44... Kd7 {[%clk 0:00:13]} 45. h5 {[%clk 0:00:01.7]} 45... Ke7 {[%clk 0:00:12.7]} 46. Kg5 {[%clk 0:00:00.9]} 46... Kf7 {[%clk 0:00:12.2]} 0-1\n",
            "time_control": "60",
            "end_time": 1741449835,
            "rated": true,
            "tcn": "mCZRgv!Tlt2Ubs92cM6EpxEvdv5ZowYIfo8!ec7YsJYQJT2TMTZTCKRKvQXQoQ45QCTCtC97d757hd7BnvBdcd!2dm2TmtTSkASRiq0SjzIzqzRQts3NzHQIsr1TxFTLCLULrsKCvCLCsrCursumslm~leIAemAHmuWGuDHQwENEDEQZFNZ0EM01",
            "uuid": "a680ff70-fc36-11ef-98f2-8bcf2701000f",
            "initial_setup": "rnbqkbnr/pppppppp/8/8/8/8/PPPPPPPP/RNBQKBNR w KQkq - 0 1",
            "fen": "8/5k2/4p3/p5KP/8/8/8/8 w - -",
            "time_class": "bullet",
            "rules": "chess",
            "white": {
                "rating": 881,
                "result": "timeout",
                "@id": "https://api.chess.com/pub/player/jorgepr1",
                "username": "Jorgepr1",
                "uuid": "22e90e32-1d95-11eb-989c-891235857dcd"
            },
            "black": {
                "rating": 889,
                "result": "win",
                "@id": "https://api.chess.com/pub/player/amonethegreat",
                "username": "AmoneTheGreat",
                "uuid": "e623d924-3772-11ed-ba94-33864f4cc01b"
            },
            "eco": "https://www.chess.com/openings/Pirc-Defense-Modern-Defense-Geller-System-2...Nf6"
        },
        {
            "url": "https://www.chess.com/game/live/136044084538",
            "pgn": "[Event \"Live Chess\"]\n[Site \"Chess.com\"]\n[Date \"2025.03.08\"]\n[Round \"-\"]\n[White \"Jorgepr1\"]\n[Black \"He4venL1ght\"]\n[Result \"0-1\"]\n[CurrentPosition \"1b1r1rk1/5ppp/p1n2qb1/1p1Q4/1P6/PB2BN1P/4RPP1/R5K1 w - -\"]\n[Timezone \"UTC\"]\n[ECO \"C53\"]\n[ECOUrl \"https://www.chess.com/openings/Giuoco-Piano-Game-Main-Line-4...d6-5.d4\"]\n[UTCDate \"2025.03.08\"]\n[UTCTime \"16:04:11\"]\n[WhiteElo \"873\"]\n[BlackElo \"897\"]\n[TimeControl \"60\"]\n[Termination \"He4venL1ght won on time\"]\n[StartTime \"16:04:11\"]\n[EndDate \"2025.03.08\"]\n[EndTime \"16:06:09\"]\n[Link \"https://www.chess.com/game/live/136044084538\"]\n\n1. e4 {[%clk 0:00:59.9]} 1... e5 {[%clk 0:00:59.9]} 2. Nf3 {[%clk 0:00:59.5]} 2... Nc6 {[%clk 0:00:58.9]} 3. Bc4 {[%clk 0:00:58.9]} 3... Bc5 {[%clk 0:00:58.2]} 4. c3 {[%clk 0:00:58.3]} 4... d6 {[%clk 0:00:57.6]} 5. d4 {[%clk 0:00:57.9]} 5... exd4 {[%clk 0:00:56.5]} 6. cxd4 {[%clk 0:00:57.8]} 6... Bb6 {[%clk 0:00:53.8]} 7. d5 {[%clk 0:00:55.1]} 7... Nce7 {[%clk 0:00:53.1]} 8. Nc3 {[%clk 0:00:54.6]} 8... Bg4 {[%clk 0:00:52.4]} 9. h3 {[%clk 0:00:52.6]} 9... Bh5 {[%clk 0:00:51.3]} 10. Bf4 {[%clk 0:00:49.7]} 10... Nf6 {[%clk 0:00:50.1]} 11. Qd3 {[%clk 0:00:45.9]} 11... Bg6 {[%clk 0:00:48.4]} 12. O-O {[%clk 0:00:43]} 12... O-O {[%clk 0:00:46.1]} 13. Rfe1 {[%clk 0:00:41.9]} 13... Ba5 {[%clk 0:00:43.4]} 14. a3 {[%clk 0:00:38.2]} 14... a6 {[%clk 0:00:41.7]} 15. b4 {[%clk 0:00:37.7]} 15... Bb6 {[%clk 0:00:40.5]} 16. Re2 {[%clk 0:00:30.7]} 16... Ba7 {[%clk 0:00:39.7]} 17. Qd2 {[%clk 0:00:26.1]} 17... b5 {[%clk 0:00:38.9]} 18. Bb3 {[%clk 0:00:24.7]} 18... Rc8 {[%clk 0:00:34.6]} 19. e5 {[%clk 0:00:23.3]} 19... dxe5 {[%clk 0:00:33.2]} 20. Bxe5 {[%clk 0:00:22.1]} 20... Nd7 {[%clk 0:00:31.5]} 21. Bd4 {[%clk 0:00:14.9]} 21... Bb8 {[%clk 0:00:27.3]} 22. Be3 {[%clk 0:00:12]} 22... c6 {[%clk 0:00:24]} 23. dxc6 {[%clk 0:00:09.6]} 23... Nxc6 {[%clk 0:00:23.9]} 24. Nd5 {[%clk 0:00:08.8]} 24... Nf6 {[%clk 0:00:19.3]} 25. Nxf6+ {[%clk 0:00:06.8]} 25... Qxf6 {[%clk 0:00:19.2]} 26. Qd5 {[%clk 0:00:03.1]} 26... Rcd8 {[%clk 0:00:16.2]} 0-1\n",
            "time_control": "60",
            "end_time": 1741449969,
            "rated": true,
            "tcn": "mC0Kgv5QfA9IksZRlBKBsBIPBJQ0bs6EpxENcD!TdtNUeg8!fePGiqWOjzGPemPWtlXHAr46CKRKDKTZKBW5BuYQJQ0QsJZTJT7TlJ67",
            "uuid": "f92ec4fd-fc36-11ef-ac41-a9c46501000f",
            "initial_setup": "rnbqkbnr/pppppppp/8/8/8/8/PPPPPPPP/RNBQKBNR w KQkq - 0 1",
            "fen": "1b1r1rk1/5ppp/p1n2qb1/1p1Q4/1P6/PB2BN1P/4RPP1/R5K1 w - -",
            "time_class": "bullet",
            "rules": "chess",
            "white": {
                "rating": 873,
                "result": "timeout",
                "@id": "https://api.chess.com/pub/player/jorgepr1",
                "username": "Jorgepr1",
                "uuid": "22e90e32-1d95-11eb-989c-891235857dcd"
            },
            "black": {
                "rating": 897,
                "result": "win",
                "@id": "https://api.chess.com/pub/player/he4venl1ght",
                "username": "He4venL1ght",
                "uuid": "78d8f224-0160-11ee-95af-71287ee83974"
            },
            "eco": "https://www.chess.com/openings/Giuoco-Piano-Game-Main-Line-4...d6-5.d4"
        },
        {
            "url": "https://www.chess.com/game/live/136044155002",
            "pgn": "[Event \"Live Chess\"]\n[Site \"Chess.com\"]\n[Date \"2025.03.08\"]\n[Round \"-\"]\n[White \"Jorgepr1\"]\n[Black \"Hwjagwbavsshy\"]\n[Result \"0-1\"]\n[CurrentPosition \"r3kb1r/1b1npppp/p2p4/8/1p6/3B2B1/PPPQNPqP/R3R1K1 w kq -\"]\n[Timezone \"UTC\"]\n[ECO \"B07\"]\n[ECOUrl \"https://www.chess.com/openings/Pirc-Defense-2.d4-Nf6-3.Nc3\"]\n[UTCDate \"2025.03.08\"]\n[UTCTime \"16:06:26\"]\n[WhiteElo \"792\"]\n[BlackElo \"821\"]\n[TimeControl \"180\"]\n[Termination \"Hwjagwbavsshy won by checkmate\"]\n[StartTime \"16:06:26\"]\n[EndDate \"2025.03.08\"]\n[EndTime \"16:07:43\"]\n[Link \"https://www.chess.com/game/live/136044155002\"]\n\n1. e4 {[%clk 0:02:59.9]} 1... d6 {[%clk 0:02:59.8]} 2. d4 {[%clk 0:02:57.5]} 2... Nf6 {[%clk 0:02:59.7]} 3. Nc3 {[%clk 0:02:55.1]} 3... a6 {[%clk 0:02:59]} 4. Nf3 {[%clk 0:02:54]} 4... b5 {[%clk 0:02:58.3]} 5. e5 {[%clk 0:02:53.3]} 5... Nfd7 {[%clk 0:02:55.3]} 6. exd6 {[%clk 0:02:51.7]} 6... cxd6 {[%clk 0:02:54.2]} 7. Bf4 {[%clk 0:02:51.3]} 7... Bb7 {[%clk 0:02:51.7]} 8. Bd3 {[%clk 0:02:49.5]} 8... Nc6 {[%clk 0:02:42.4]} 9. O-O {[%clk 0:02:48.1]} 9... Qb6 {[%clk 0:02:37.7]} 10. Re1 {[%clk 0:02:46]} 10... Nxd4 {[%clk 0:02:35.2]} 11. Nxd4 {[%clk 0:02:42.9]} 11... Qxd4 {[%clk 0:02:35.1]} 12. Bg3 {[%clk 0:02:37.4]} 12... b4 {[%clk 0:02:30.7]} 13. Ne2 {[%clk 0:02:35.5]} 13... Qd5 {[%clk 0:02:29.1]} 14. Qd2 {[%clk 0:02:23.5]} 14... Qxg2# {[%clk 0:02:27.5]} 0-1\n",
            "time_control": "180",
            "end_time": 1741450063,
            "rated": true,
            "tcn": "mCZRlB!TbsWOgvXHCKTZKRYRcD6Xft5Qeg7PfeQBvBPBDwHzsmBJdlJo",
            "uuid": "49bcdf10-fc37-11ef-ac41-a9c46501000f",
            "initial_setup": "rnbqkbnr/pppppppp/8/8/8/8/PPPPPPPP/RNBQKBNR w KQkq - 0 1",
            "fen": "r3kb1r/1b1npppp/p2p4/8/1p6/3B2B1/PPPQNPqP/R3R1K1 w kq -",
            "time_class": "blitz",
            "rules": "chess",
            "white": {
                "rating": 792,
                "result": "checkmated",
                "@id": "https://api.chess.com/pub/player/jorgepr1",
                "username": "Jorgepr1",
                "uuid": "22e90e32-1d95-11eb-989c-891235857dcd"
            },
            "black": {
                "rating": 821,
                "result": "win",
                "@id": "https://api.chess.com/pub/player/hwjagwbavsshy",
                "username": "Hwjagwbavsshy",
                "uuid": "ce22ebae-e9e9-11ef-a1f0-f58f010b2bb9"
            },
            "eco": "https://www.chess.com/openings/Pirc-Defense-2.d4-Nf6-3.Nc3"
        },
        {
            "url": "https://www.chess.com/game/live/136044200762",
            "pgn": "[Event \"Live Chess\"]\n[Site \"Chess.com\"]\n[Date \"2025.03.08\"]\n[Round \"-\"]\n[White \"Redfox007\"]\n[Black \"Jorgepr1\"]\n[Result \"0-1\"]\n[CurrentPosition \"8/8/1b6/4k1p1/6P1/pB6/6K1/8 w - -\"]\n[Timezone \"UTC\"]\n[ECO \"D02\"]\n[ECOUrl \"https://www.chess.com/openings/Queens-Pawn-Opening-Krause-Variation\"]\n[UTCDate \"2025.03.08\"]\n[UTCTime \"16:07:54\"]\n[WhiteElo \"771\"]\n[BlackElo \"800\"]\n[TimeControl \"180\"]\n[Termination \"Jorgepr1 won on time\"]\n[StartTime \"16:07:54\"]\n[EndDate \"2025.03.08\"]\n[EndTime \"16:14:13\"]\n[Link \"https://www.chess.com/game/live/136044200762\"]\n\n1. d4 {[%clk 0:02:58.4]} 1... d5 {[%clk 0:02:58.5]} 2. Nf3 {[%clk 0:02:56.8]} 2... c5 {[%clk 0:02:57.7]} 3. g3 {[%clk 0:02:55.5]} 3... Bf5 {[%clk 0:02:54.6]} 4. Bg2 {[%clk 0:02:53.9]} 4... e6 {[%clk 0:02:54.1]} 5. dxc5 {[%clk 0:02:53.1]} 5... Bxc5 {[%clk 0:02:52]} 6. O-O {[%clk 0:02:51.6]} 6... Nf6 {[%clk 0:02:51.5]} 7. e3 {[%clk 0:02:50.9]} 7... Nc6 {[%clk 0:02:50.9]} 8. Nbd2 {[%clk 0:02:49.6]} 8... O-O {[%clk 0:02:49.3]} 9. b3 {[%clk 0:02:47.8]} 9... Qd6 {[%clk 0:02:48.4]} 10. c4 {[%clk 0:02:47]} 10... dxc4 {[%clk 0:02:46.2]} 11. bxc4 {[%clk 0:02:45.2]} 11... Rfd8 {[%clk 0:02:43.4]} 12. Bb2 {[%clk 0:02:43.8]} 12... Ne4 {[%clk 0:02:39.4]} 13. Qa4 {[%clk 0:02:39.2]} 13... Nxd2 {[%clk 0:02:31.6]} 14. Rad1 {[%clk 0:02:35.3]} 14... Nxf3+ {[%clk 0:02:24.8]} 15. Bxf3 {[%clk 0:02:34]} 15... Qc7 {[%clk 0:02:19.7]} 16. e4 {[%clk 0:02:28.3]} 16... Bg6 {[%clk 0:02:16.5]} 17. Kg2 {[%clk 0:02:25.2]} 17... Rd6 {[%clk 0:02:11.5]} 18. e5 {[%clk 0:02:22.9]} 18... Nxe5 {[%clk 0:02:03.4]} 19. Rxd6 {[%clk 0:02:20.4]} 19... Qxd6 {[%clk 0:01:59.2]} 20. Rd1 {[%clk 0:02:15.3]} 20... Qc7 {[%clk 0:01:55.8]} 21. Bxe5 {[%clk 0:02:12.6]} 21... Qxe5 {[%clk 0:01:53.4]} 22. Bxb7 {[%clk 0:02:11.1]} 22... Rb8 {[%clk 0:01:47.8]} 23. Bf3 {[%clk 0:02:05.5]} 23... Qc7 {[%clk 0:01:42.6]} 24. a3 {[%clk 0:01:51]} 24... h6 {[%clk 0:01:41.4]} 25. Qa6 {[%clk 0:01:44.3]} 25... Bb6 {[%clk 0:01:37.2]} 26. c5 {[%clk 0:01:40.2]} 26... Qxc5 {[%clk 0:01:29.4]} 27. Qe2 {[%clk 0:01:32.7]} 27... Rd8 {[%clk 0:01:22.5]} 28. Rxd8+ {[%clk 0:01:30.7]} 28... Bxd8 {[%clk 0:01:22.4]} 29. a4 {[%clk 0:01:28.6]} 29... Bb6 {[%clk 0:01:19.3]} 30. h4 {[%clk 0:01:25.8]} 30... Qb4 {[%clk 0:01:08.3]} 31. Kh3 {[%clk 0:01:16.3]} 31... Qxa4 {[%clk 0:01:03.8]} 32. Qe5 {[%clk 0:01:06.5]} 32... Bf5+ {[%clk 0:00:55.3]} 33. g4 {[%clk 0:01:04.7]} 33... Bg6 {[%clk 0:00:49.4]} 34. Qb8+ {[%clk 0:01:02.8]} 34... Kh7 {[%clk 0:00:47.5]} 35. Qb7 {[%clk 0:00:59.7]} 35... Qf4 {[%clk 0:00:41.5]} 36. Kg2 {[%clk 0:00:46.9]} 36... Qf6 {[%clk 0:00:25.3]} 37. h5 {[%clk 0:00:43]} 37... Bd3 {[%clk 0:00:19.3]} 38. Qd7 {[%clk 0:00:40.1]} 38... Bb5 {[%clk 0:00:17.1]} 39. Be4+ {[%clk 0:00:36.6]} 39... g6 {[%clk 0:00:15.5]} 40. Qd2 {[%clk 0:00:30.7]} 40... Bc6 {[%clk 0:00:13.3]} 41. hxg6+ {[%clk 0:00:27.6]} 41... fxg6 {[%clk 0:00:10.1]} 42. Bxc6 {[%clk 0:00:25]} 42... Qg5 {[%clk 0:00:08.7]} 43. Qxg5 {[%clk 0:00:22]} 43... hxg5 {[%clk 0:00:08.6]} 44. Bd7 {[%clk 0:00:19.2]} 44... Kg7 {[%clk 0:00:08]} 45. Bxe6 {[%clk 0:00:17.3]} 45... Kf6 {[%clk 0:00:07.5]} 46. Bd7 {[%clk 0:00:13.1]} 46... Ke5 {[%clk 0:00:06.4]} 47. f3 {[%clk 0:00:11.1]} 47... Kf4 {[%clk 0:00:05.7]} 48. Be8 {[%clk 0:00:09.7]} 48... a5 {[%clk 0:00:02.5]} 49. Bxg6 {[%clk 0:00:08.4]} 49... a4 {[%clk 0:00:02]} 50. Bf7 {[%clk 0:00:06.5]} 50... a3 {[%clk 0:00:01.6]} 51. Kh3 {[%clk 0:00:03]} 51... Kxf3 {[%clk 0:00:00.5]} 52. Bb3 {[%clk 0:00:01.8]} 52... Kf4 {[%clk 0:00:00.4]} 53. Kg2 {[%clk 0:00:00.4]} 53... Ke5 {[%clk 0:00:00.3]} 0-1\n",
            "time_control": "180",
            "end_time": 1741450453,
            "rated": true,
            "tcn": "lBZJgvYIow6Lfo0SBI9Ieg!Tmu5Qbl8!jr7RkAJArA97cjTCdyCladlvovRYuCLUgo7RCKQKdRYRfdRYjKYKvX45XvKYiq3VyOIPAIYIOm57d7P7qy7PpFIzoxzymKULwELUK5!35XyDxoDTFNUtXZtHvC2UZlHQNU1UCQTMlMVMQZ32ZS2TSZTKnvKDZ8WG8UGyU1yqoxDv1rvDxoDK",
            "uuid": "7e662a21-fc37-11ef-ba3e-a318ff01000f",
            "initial_setup": "rnbqkbnr/pppppppp/8/8/8/8/PPPPPPPP/RNBQKBNR w KQkq - 0 1",
            "fen": "8/8/1b6/4k1p1/6P1/pB6/6K1/8 w - -",
            "time_class": "blitz",
            "rules": "chess",
            "white": {
                "rating": 771,
                "result": "timeout",
                "@id": "https://api.chess.com/pub/player/redfox007",
                "username": "Redfox007",
                "uuid": "62ce8440-1edc-11e0-8027-000000000000"
            },
            "black": {
                "rating": 800,
                "result": "win",
                "@id": "https://api.chess.com/pub/player/jorgepr1",
                "username": "Jorgepr1",
                "uuid": "22e90e32-1d95-11eb-989c-891235857dcd"
            },
            "eco": "https://www.chess.com/openings/Queens-Pawn-Opening-Krause-Variation"
        },
        {
            "url": "https://www.chess.com/game/live/136057001842",
            "pgn": "[Event \"Live Chess\"]\n[Site \"Chess.com\"]\n[Date \"2025.03.08\"]\n[Round \"-\"]\n[White \"RobertGermany\"]\n[Black \"Jorgepr1\"]\n[Result \"0-1\"]\n[CurrentPosition \"r7/ppp1kP2/7Q/3p4/1P4bn/8/P4bq1/5R1K w - -\"]\n[Timezone \"UTC\"]\n[ECO \"A00\"]\n[ECOUrl \"https://www.chess.com/openings/Kings-Fianchetto-Opening...2.Bg2-Nf6-3.d3-d5\"]\n[UTCDate \"2025.03.08\"]\n[UTCTime \"23:42:51\"]\n[WhiteElo \"774\"]\n[BlackElo \"808\"]\n[TimeControl \"180\"]\n[Termination \"Jorgepr1 won by checkmate\"]\n[StartTime \"23:42:51\"]\n[EndDate \"2025.03.08\"]\n[EndTime \"23:48:20\"]\n[Link \"https://www.chess.com/game/live/136057001842\"]\n\n1. d3 {[%clk 0:02:58.8]} 1... d5 {[%clk 0:02:58.2]} 2. g3 {[%clk 0:02:58.1]} 2... e5 {[%clk 0:02:57.6]} 3. Bg2 {[%clk 0:02:57.8]} 3... Nf6 {[%clk 0:02:55.3]} 4. h3 {[%clk 0:02:57.7]} 4... Nc6 {[%clk 0:02:54.3]} 5. Bg5 {[%clk 0:02:56.7]} 5... h6 {[%clk 0:02:51.8]} 6. Bd2 {[%clk 0:02:54.2]} 6... Bc5 {[%clk 0:02:51.2]} 7. c3 {[%clk 0:02:50.5]} 7... O-O {[%clk 0:02:49.5]} 8. Qc1 {[%clk 0:02:49]} 8... Be6 {[%clk 0:02:40.6]} 9. Bxh6 {[%clk 0:02:47]} 9... gxh6 {[%clk 0:02:35.8]} 10. Qxh6 {[%clk 0:02:46.3]} 10... Qe7 {[%clk 0:02:26.6]} 11. Nf3 {[%clk 0:02:43.4]} 11... Nh7 {[%clk 0:02:23.3]} 12. h4 {[%clk 0:02:41.1]} 12... Qf6 {[%clk 0:02:20.4]} 13. Qd2 {[%clk 0:02:35.6]} 13... Bg4 {[%clk 0:02:17.1]} 14. b4 {[%clk 0:02:31.9]} 14... Bb6 {[%clk 0:02:15]} 15. d4 {[%clk 0:02:21.3]} 15... exd4 {[%clk 0:02:06.5]} 16. cxd4 {[%clk 0:02:17.8]} 16... Rfe8 {[%clk 0:02:01.2]} 17. O-O {[%clk 0:02:11.6]} 17... Kf8 {[%clk 0:01:52.5]} 18. Ng5 {[%clk 0:02:01.5]} 18... Nxg5 {[%clk 0:01:49.5]} 19. hxg5 {[%clk 0:02:00]} 19... Qxd4 {[%clk 0:01:37.4]} 20. Qc2 {[%clk 0:01:47.2]} 20... Rxe2 {[%clk 0:01:14.2]} 21. Nd2 {[%clk 0:01:39.1]} 21... Rxd2 {[%clk 0:01:09.6]} 22. Qh7 {[%clk 0:01:36.3]} 22... Rxf2 {[%clk 0:01:02]} 23. Kh2 {[%clk 0:01:30.7]} 23... Ne5 {[%clk 0:00:39.1]} 24. Rad1 {[%clk 0:01:28.8]} 24... Nf3+ {[%clk 0:00:37.2]} 25. Kh1 {[%clk 0:01:16.7]} 25... Qe5 {[%clk 0:00:27.2]} 26. Rxf2 {[%clk 0:01:09.6]} 26... Bxf2 {[%clk 0:00:23.6]} 27. Rf1 {[%clk 0:01:07]} 27... Qxg3 {[%clk 0:00:19.3]} 28. Qh6+ {[%clk 0:00:51.6]} 28... Ke7 {[%clk 0:00:14.2]} 29. g6 {[%clk 0:00:39.3]} 29... Nh4 {[%clk 0:00:12.8]} 30. gxf7 {[%clk 0:00:32.8]} 30... Qxg2# {[%clk 0:00:08.2]} 0-1\n",
            "time_control": "180",
            "end_time": 1741477700,
            "rated": true,
            "accuracies": {
                "white": 59.58,
                "black": 74.57
            },
            "tcn": "ltZJow0Kfo!Tpx5QcM3VMl9Iks8!dc6SlV2VcV70gvT3xF0TVlSEjzIPtBKBsB98eg!9vM3MFMTBlk8mblmlk3lngpQKadKvphBKfnPndfKw3V90MUvFU1wo",
            "uuid": "0cd9e950-fc77-11ef-b33b-b4382c01000f",
            "initial_setup": "rnbqkbnr/pppppppp/8/8/8/8/PPPPPPPP/RNBQKBNR w KQkq - 0 1",
            "fen": "r7/ppp1kP2/7Q/3p4/1P4bn/8/P4bq1/5R1K w - -",
            "time_class": "blitz",
            "rules": "chess",
            "white": {
                "rating": 774,
                "result": "checkmated",
                "@id": "https://api.chess.com/pub/player/robertgermany",
                "username": "RobertGermany",
                "uuid": "4c79d642-59cb-11eb-91e8-83dc6042f765"
            },
            "black": {
                "rating": 808,
                "result": "win",
                "@id": "https://api.chess.com/pub/player/jorgepr1",
                "username": "Jorgepr1",
                "uuid": "22e90e32-1d95-11eb-989c-891235857dcd"
            },
            "eco": "https://www.chess.com/openings/Kings-Fianchetto-Opening...2.Bg2-Nf6-3.d3-d5"
        },
        {
            "url": "https://www.chess.com/game/live/136062102212",
            "pgn": "[Event \"Live Chess\"]\n[Site \"Chess.com\"]\n[Date \"2025.03.09\"]\n[Round \"-\"]\n[White \"Jorgepr1\"]\n[Black \"Drewvinski\"]\n[Result \"1-0\"]\n[CurrentPosition \"2Q5/5ppk/6rp/8/4P3/1BQPKN2/8/8 b - -\"]\n[Timezone \"UTC\"]\n[ECO \"C50\"]\n[ECOUrl \"https://www.chess.com/openings/Giuoco-Piano-Game...6.d3-h6-7.Re1-O-O-8.Nbd2\"]\n[UTCDate \"2025.03.09\"]\n[UTCTime \"04:21:18\"]\n[WhiteElo \"816\"]\n[BlackElo \"810\"]\n[TimeControl \"180\"]\n[Termination \"Jorgepr1 won - game abandoned\"]\n[StartTime \"04:21:18\"]\n[EndDate \"2025.03.09\"]\n[EndTime \"04:24:41\"]\n[Link \"https://www.chess.com/game/live/136062102212\"]\n\n1. e4 {[%clk 0:02:58.8]} 1... e5 {[%clk 0:02:59.3]} 2. Nf3 {[%clk 0:02:58.5]} 2... Nc6 {[%clk 0:02:57.6]} 3. Bc4 {[%clk 0:02:57.9]} 3... h6 {[%clk 0:02:56.2]} 4. c3 {[%clk 0:02:57.2]} 4... Nf6 {[%clk 0:02:55.6]} 5. d3 {[%clk 0:02:56.2]} 5... Bc5 {[%clk 0:02:53.8]} 6. O-O {[%clk 0:02:55.5]} 6... O-O {[%clk 0:02:51.1]} 7. Re1 {[%clk 0:02:55.1]} 7... d6 {[%clk 0:02:50.2]} 8. Nbd2 {[%clk 0:02:54.3]} 8... Ng4 {[%clk 0:02:48.7]} 9. Re2 {[%clk 0:02:50.7]} 9... Qf6 {[%clk 0:02:42.4]} 10. h3 {[%clk 0:02:46.8]} 10... Bxf2+ {[%clk 0:02:34.5]} 11. Rxf2 {[%clk 0:02:44.6]} 11... Nxf2 {[%clk 0:02:33.9]} 12. Kxf2 {[%clk 0:02:44.5]} 12... Bxh3 {[%clk 0:02:21.6]} 13. gxh3 {[%clk 0:02:41.5]} 13... Qf4 {[%clk 0:02:18]} 14. Nf1 {[%clk 0:02:34.4]} 14... Ne7 {[%clk 0:02:16.6]} 15. Ng3 {[%clk 0:02:33]} 15... Ng6 {[%clk 0:02:15.2]} 16. Bxf4 {[%clk 0:02:28.5]} 16... Nxf4 {[%clk 0:02:14]} 17. Ke3 {[%clk 0:02:21.5]} 17... Nxh3 {[%clk 0:02:12.4]} 18. Ne2 {[%clk 0:02:16.5]} 18... Nf4 {[%clk 0:02:11.5]} 19. Nxf4 {[%clk 0:02:15.2]} 19... exf4+ {[%clk 0:02:11.4]} 20. Kxf4 {[%clk 0:02:14.7]} 20... a6 {[%clk 0:02:09.3]} 21. Qg1 {[%clk 0:02:10.5]} 21... b5 {[%clk 0:02:07.7]} 22. Bb3 {[%clk 0:02:08.9]} 22... c5 {[%clk 0:02:06.4]} 23. Ke3 {[%clk 0:02:07.5]} 23... Rac8 {[%clk 0:02:03.9]} 24. c4 {[%clk 0:02:04.7]} 24... b4 {[%clk 0:02:01.7]} 25. a3 {[%clk 0:02:00.7]} 25... a5 {[%clk 0:01:59.6]} 26. axb4 {[%clk 0:01:59.6]} 26... axb4 {[%clk 0:01:58.6]} 27. Ra6 {[%clk 0:01:57.9]} 27... Rfd8 {[%clk 0:01:55.7]} 28. Qg3 {[%clk 0:01:56.5]} 28... Ra8 {[%clk 0:01:50.3]} 29. Rxd6 {[%clk 0:01:53.9]} 29... Rxd6 {[%clk 0:01:49]} 30. Qxd6 {[%clk 0:01:53.8]} 30... Ra1 {[%clk 0:01:45.6]} 31. Qxc5 {[%clk 0:01:51.2]} 31... Rb1 {[%clk 0:01:40.4]} 32. Qxb4 {[%clk 0:01:50.1]} 32... Rxb2 {[%clk 0:01:39.6]} 33. Qc3 {[%clk 0:01:45.9]} 33... Rg2 {[%clk 0:01:37]} 34. c5 {[%clk 0:01:44.4]} 34... Rg3 {[%clk 0:01:34.4]} 35. c6 {[%clk 0:01:43.1]} 35... Kh7 {[%clk 0:01:31.5]} 36. c7 {[%clk 0:01:41.8]} 36... Rg6 {[%clk 0:01:30.5]} 37. c8=Q {[%clk 0:01:39.9]} 1-0\n",
            "time_control": "180",
            "end_time": 1741494281,
            "rated": true,
            "tcn": "mC0Kgv5QfA3Vks!Tlt9Ieg8!feZRblTEem7TpxInmnEngn6xoxTDlfQ0fw0UcDUDnuDxwmxDmDKDuDWOdgXHArYIDu46sAHziqOGqzGzaO97gw64OR7RwR4aRIabIzbjzsjoAIowIQ!3QYwUY~",
            "uuid": "f2fdf7cc-fc9d-11ef-ba3e-a318ff01000f",
            "initial_setup": "rnbqkbnr/pppppppp/8/8/8/8/PPPPPPPP/RNBQKBNR w KQkq - 0 1",
            "fen": "2Q5/5ppk/6rp/8/4P3/1BQPKN2/8/8 b - -",
            "time_class": "blitz",
            "rules": "chess",
            "white": {
                "rating": 816,
                "result": "win",
                "@id": "https://api.chess.com/pub/player/jorgepr1",
                "username": "Jorgepr1",
                "uuid": "22e90e32-1d95-11eb-989c-891235857dcd"
            },
            "black": {
                "rating": 810,
                "result": "abandoned",
                "@id": "https://api.chess.com/pub/player/drewvinski",
                "username": "Drewvinski",
                "uuid": "26527632-2d0f-11ec-b8c3-e52ef9a54b6e"
            },
            "eco": "https://www.chess.com/openings/Giuoco-Piano-Game...6.d3-h6-7.Re1-O-O-8.Nbd2"
        },
        {
            "url": "https://www.chess.com/game/live/136062254608",
            "pgn": "[Event \"Live Chess\"]\n[Site \"Chess.com\"]\n[Date \"2025.03.09\"]\n[Round \"-\"]\n[White \"Hajer_81\"]\n[Black \"Jorgepr1\"]\n[Result \"1-0\"]\n[CurrentPosition \"1r3rk1/p1p1nppp/8/8/3QB1b1/2N2N2/PPP3PP/R4RK1 b - -\"]\n[Timezone \"UTC\"]\n[ECO \"C50\"]\n[ECOUrl \"https://www.chess.com/openings/Giuoco-Piano-Game-4.O-O-Nf6-5.Nc3-d6\"]\n[UTCDate \"2025.03.09\"]\n[UTCTime \"04:29:45\"]\n[WhiteElo \"843\"]\n[BlackElo \"808\"]\n[TimeControl \"180\"]\n[Termination \"Hajer_81 won by resignation\"]\n[StartTime \"04:29:45\"]\n[EndDate \"2025.03.09\"]\n[EndTime \"04:31:04\"]\n[Link \"https://www.chess.com/game/live/136062254608\"]\n\n1. e4 {[%clk 0:02:59.9]} 1... e5 {[%clk 0:02:58.2]} 2. Nf3 {[%clk 0:02:58.8]} 2... Nc6 {[%clk 0:02:57.8]} 3. Bc4 {[%clk 0:02:58.2]} 3... Bc5 {[%clk 0:02:57.3]} 4. O-O {[%clk 0:02:57.5]} 4... d6 {[%clk 0:02:56.9]} 5. Nc3 {[%clk 0:02:56.7]} 5... Nf6 {[%clk 0:02:56.5]} 6. d3 {[%clk 0:02:56]} 6... O-O {[%clk 0:02:55.8]} 7. Be3 {[%clk 0:02:55.3]} 7... Bxe3 {[%clk 0:02:54]} 8. fxe3 {[%clk 0:02:55.2]} 8... Bg4 {[%clk 0:02:50.9]} 9. d4 {[%clk 0:02:54]} 9... exd4 {[%clk 0:02:49.2]} 10. exd4 {[%clk 0:02:53.1]} 10... d5 {[%clk 0:02:48.6]} 11. exd5 {[%clk 0:02:52.1]} 11... Nxd5 {[%clk 0:02:46.6]} 12. Bxd5 {[%clk 0:02:51.2]} 12... Ne7 {[%clk 0:02:41.2]} 13. Bxb7 {[%clk 0:02:47.2]} 13... Rb8 {[%clk 0:02:39.3]} 14. Be4 {[%clk 0:02:33.7]} 14... Qxd4+ {[%clk 0:02:24.9]} 15. Qxd4 {[%clk 0:02:29.5]} 1-0\n",
            "time_control": "180",
            "end_time": 1741494664,
            "rated": true,
            "tcn": "mC0Kgv5QfA9IegZRbs!Tlt8!cuIunu6EtBKBuBRJCJTJAJQ0JX45XC7BdB",
            "uuid": "20f102ab-fc9f-11ef-ac41-a9c46501000f",
            "initial_setup": "rnbqkbnr/pppppppp/8/8/8/8/PPPPPPPP/RNBQKBNR w KQkq - 0 1",
            "fen": "1r3rk1/p1p1nppp/8/8/3QB1b1/2N2N2/PPP3PP/R4RK1 b - -",
            "time_class": "blitz",
            "rules": "chess",
            "white": {
                "rating": 843,
                "result": "win",
                "@id": "https://api.chess.com/pub/player/hajer_81",
                "username": "Hajer_81",
                "uuid": "e00fcd3e-6ef9-11ef-828f-d5f8b54b6d2b"
            },
            "black": {
                "rating": 808,
                "result": "resigned",
                "@id": "https://api.chess.com/pub/player/jorgepr1",
                "username": "Jorgepr1",
                "uuid": "22e90e32-1d95-11eb-989c-891235857dcd"
            },
            "eco": "https://www.chess.com/openings/Giuoco-Piano-Game-4.O-O-Nf6-5.Nc3-d6"
        },
        {
            "url": "https://www.chess.com/game/live/136062285666",
            "pgn": "[Event \"Live Chess\"]\n[Site \"Chess.com\"]\n[Date \"2025.03.09\"]\n[Round \"-\"]\n[White \"Jorgepr1\"]\n[Black \"AlienTactition\"]\n[Result \"1-0\"]\n[CurrentPosition \"r1bq1r1k/ppp2pQ1/2n1N3/2bpp3/2B1P3/2PP4/PP3PPP/RN2K2R b KQ -\"]\n[Timezone \"UTC\"]\n[ECO \"C53\"]\n[ECOUrl \"https://www.chess.com/openings/Giuoco-Piano-Game-Main-Line-Giuoco-Pianissimo-Variation-5...O-O-6.Bg5-h6-7.Bh4\"]\n[UTCDate \"2025.03.09\"]\n[UTCTime \"04:31:28\"]\n[WhiteElo \"816\"]\n[BlackElo \"818\"]\n[TimeControl \"180\"]\n[Termination \"Jorgepr1 won by checkmate\"]\n[StartTime \"04:31:28\"]\n[EndDate \"2025.03.09\"]\n[EndTime \"04:32:39\"]\n[Link \"https://www.chess.com/game/live/136062285666\"]\n\n1. e4 {[%clk 0:02:57]} 1... e5 {[%clk 0:02:58.9]} 2. Nf3 {[%clk 0:02:54.7]} 2... Nc6 {[%clk 0:02:57.3]} 3. Bc4 {[%clk 0:02:54.2]} 3... Bc5 {[%clk 0:02:52.9]} 4. c3 {[%clk 0:02:53.1]} 4... Nf6 {[%clk 0:02:51.3]} 5. d3 {[%clk 0:02:52.3]} 5... O-O {[%clk 0:02:49.1]} 6. Bg5 {[%clk 0:02:51.7]} 6... h6 {[%clk 0:02:46.4]} 7. Bh4 {[%clk 0:02:50.2]} 7... g5 {[%clk 0:02:45.2]} 8. Bxg5 {[%clk 0:02:41.2]} 8... hxg5 {[%clk 0:02:42.9]} 9. Nxg5 {[%clk 0:02:41.1]} 9... Ng4 {[%clk 0:02:38.3]} 10. Qxg4 {[%clk 0:02:37.2]} 10... d5 {[%clk 0:02:35.9]} 11. Ne6+ {[%clk 0:02:31]} 11... Kh8 {[%clk 0:02:30.6]} 12. Qg7# {[%clk 0:02:26.4]} 1-0\n",
            "time_control": "180",
            "end_time": 1741494759,
            "rated": true,
            "tcn": "mC0Kgv5QfA9Iks!Tlt8!cM3VMF2MFMVMvMTEdEZJMS!?E2",
            "uuid": "5e41930d-fc9f-11ef-98f2-8bcf2701000f",
            "initial_setup": "rnbqkbnr/pppppppp/8/8/8/8/PPPPPPPP/RNBQKBNR w KQkq - 0 1",
            "fen": "r1bq1r1k/ppp2pQ1/2n1N3/2bpp3/2B1P3/2PP4/PP3PPP/RN2K2R b KQ -",
            "time_class": "blitz",
            "rules": "chess",
            "white": {
                "rating": 816,
                "result": "win",
                "@id": "https://api.chess.com/pub/player/jorgepr1",
                "username": "Jorgepr1",
                "uuid": "22e90e32-1d95-11eb-989c-891235857dcd"
            },
            "black": {
                "rating": 818,
                "result": "checkmated",
                "@id": "https://api.chess.com/pub/player/alientactition",
                "username": "AlienTactition",
                "uuid": "fa5d8ce6-dfd1-11ef-b65c-4581e1985646"
            },
            "eco": "https://www.chess.com/openings/Giuoco-Piano-Game-Main-Line-Giuoco-Pianissimo-Variation-5...O-O-6.Bg5-h6-7.Bh4"
        },
        {
            "url": "https://www.chess.com/game/live/136062315768",
            "pgn": "[Event \"Live Chess\"]\n[Site \"Chess.com\"]\n[Date \"2025.03.09\"]\n[Round \"-\"]\n[White \"MaTaTiTa77\"]\n[Black \"Jorgepr1\"]\n[Result \"0-1\"]\n[CurrentPosition \"1kr4r/pp3pp1/4p1p1/8/1P6/P1B5/2R1QPP1/2R2K1q w - -\"]\n[Timezone \"UTC\"]\n[ECO \"D02\"]\n[ECOUrl \"https://www.chess.com/openings/Queens-Pawn-Opening-Krause-Variation-3.c3\"]\n[UTCDate \"2025.03.09\"]\n[UTCTime \"04:33:06\"]\n[WhiteElo \"821\"]\n[BlackElo \"824\"]\n[TimeControl \"180\"]\n[Termination \"Jorgepr1 won by checkmate\"]\n[StartTime \"04:33:06\"]\n[EndDate \"2025.03.09\"]\n[EndTime \"04:35:30\"]\n[Link \"https://www.chess.com/game/live/136062315768\"]\n\n1. d4 {[%clk 0:02:57.7]} 1... d5 {[%clk 0:02:58.4]} 2. Nf3 {[%clk 0:02:57]} 2... c5 {[%clk 0:02:58]} 3. c3 {[%clk 0:02:55.5]} 3... Bf5 {[%clk 0:02:56.7]} 4. e3 {[%clk 0:02:54.6]} 4... e6 {[%clk 0:02:56.3]} 5. Nh4 {[%clk 0:02:53.6]} 5... Bg6 {[%clk 0:02:54.2]} 6. Nxg6 {[%clk 0:02:51.9]} 6... hxg6 {[%clk 0:02:54.1]} 7. Bd3 {[%clk 0:02:51.3]} 7... Nf6 {[%clk 0:02:53.7]} 8. Nd2 {[%clk 0:02:50.4]} 8... cxd4 {[%clk 0:02:52.8]} 9. cxd4 {[%clk 0:02:49.3]} 9... Bb4 {[%clk 0:02:51.4]} 10. Qe2 {[%clk 0:02:47.4]} 10... Nc6 {[%clk 0:02:50.2]} 11. O-O {[%clk 0:02:44.8]} 11... Qd6 {[%clk 0:02:48.8]} 12. a3 {[%clk 0:02:43.8]} 12... Ba5 {[%clk 0:02:45.9]} 13. b4 {[%clk 0:02:39.9]} 13... Bb6 {[%clk 0:02:44.7]} 14. e4 {[%clk 0:02:37]} 14... dxe4 {[%clk 0:02:43.5]} 15. Nxe4 {[%clk 0:02:36.9]} 15... Nxe4 {[%clk 0:02:40.3]} 16. Bxe4 {[%clk 0:02:35.3]} 16... Bxd4 {[%clk 0:02:35.9]} 17. Bxc6+ {[%clk 0:02:27.6]} 17... Qxc6 {[%clk 0:02:32.1]} 18. Ra2 {[%clk 0:02:25.3]} 18... O-O-O {[%clk 0:02:19.2]} 19. Rc2 {[%clk 0:02:21.3]} 19... Bc3 {[%clk 0:02:17.8]} 20. Bb2 {[%clk 0:02:09.4]} 20... Kb8 {[%clk 0:02:12.9]} 21. Bxc3 {[%clk 0:01:57]} 21... Rc8 {[%clk 0:02:09.6]} 22. Rb1 {[%clk 0:01:53.9]} 22... Qc7 {[%clk 0:02:04]} 23. Rbc1 {[%clk 0:01:51]} 23... Qxh2+ {[%clk 0:02:03.3]} 24. Kf1 {[%clk 0:01:46.2]} 24... Qh1# {[%clk 0:02:02.5]} 0-1\n",
            "time_control": "180",
            "end_time": 1741494930,
            "rated": true,
            "tcn": "lBZJgvYIks6Lmu0SvFLUFU3Uft!TblIBsB9zdm5Qeg7RiqzGjzGPuCJClCTCtCPBCQRQai86ikBscj65js76fbQYbcYpgfph",
            "uuid": "98c39a79-fc9f-11ef-ba3e-a318ff01000f",
            "initial_setup": "rnbqkbnr/pppppppp/8/8/8/8/PPPPPPPP/RNBQKBNR w KQkq - 0 1",
            "fen": "1kr4r/pp3pp1/4p1p1/8/1P6/P1B5/2R1QPP1/2R2K1q w - -",
            "time_class": "blitz",
            "rules": "chess",
            "white": {
                "rating": 821,
                "result": "checkmated",
                "@id": "https://api.chess.com/pub/player/matatita77",
                "username": "MaTaTiTa77",
                "uuid": "b8f6b2f8-3232-11ee-a36a-638fd6dda269"
            },
            "black": {
                "rating": 824,
                "result": "win",
                "@id": "https://api.chess.com/pub/player/jorgepr1",
                "username": "Jorgepr1",
                "uuid": "22e90e32-1d95-11eb-989c-891235857dcd"
            },
            "eco": "https://www.chess.com/openings/Queens-Pawn-Opening-Krause-Variation-3.c3"
        },
        {
            "url": "https://www.chess.com/game/live/136062378652",
            "pgn": "[Event \"Live Chess\"]\n[Site \"Chess.com\"]\n[Date \"2025.03.09\"]\n[Round \"-\"]\n[White \"pitudoArana\"]\n[Black \"Jorgepr1\"]\n[Result \"0-1\"]\n[CurrentPosition \"8/7p/5np1/4k3/5p1P/5P2/6K1/8 w - -\"]\n[Timezone \"UTC\"]\n[ECO \"D05\"]\n[ECOUrl \"https://www.chess.com/openings/Colle-System...4.b3-c5-5.Bb2-Nc6\"]\n[UTCDate \"2025.03.09\"]\n[UTCTime \"04:36:34\"]\n[WhiteElo \"808\"]\n[BlackElo \"832\"]\n[TimeControl \"180\"]\n[Termination \"Jorgepr1 won on time\"]\n[StartTime \"04:36:34\"]\n[EndDate \"2025.03.09\"]\n[EndTime \"04:42:47\"]\n[Link \"https://www.chess.com/game/live/136062378652\"]\n\n1. d4 {[%clk 0:02:59.9]} 1... d5 {[%clk 0:02:58.6]} 2. Nf3 {[%clk 0:02:59.3]} 2... c5 {[%clk 0:02:58.1]} 3. b3 {[%clk 0:02:57.8]} 3... e6 {[%clk 0:02:57.6]} 4. Bb2 {[%clk 0:02:55.6]} 4... Nc6 {[%clk 0:02:57.1]} 5. e3 {[%clk 0:02:53.8]} 5... Nf6 {[%clk 0:02:53.5]} 6. Be2 {[%clk 0:02:51]} 6... b6 {[%clk 0:02:52.4]} 7. Nbd2 {[%clk 0:02:50.1]} 7... Bb7 {[%clk 0:02:50.5]} 8. c4 {[%clk 0:02:48.8]} 8... cxd4 {[%clk 0:02:47.1]} 9. Nxd4 {[%clk 0:02:46.1]} 9... Bd6 {[%clk 0:02:42.2]} 10. N2f3 {[%clk 0:02:40.3]} 10... O-O {[%clk 0:02:37.1]} 11. Rc1 {[%clk 0:02:26.3]} 11... e5 {[%clk 0:02:35.5]} 12. Nf5 {[%clk 0:02:23.7]} 12... dxc4 {[%clk 0:02:31.7]} 13. bxc4 {[%clk 0:02:20.6]} 13... Bb4+ {[%clk 0:02:28.1]} 14. Bc3 {[%clk 0:02:14.4]} 14... Qxd1+ {[%clk 0:02:19.6]} 15. Bxd1 {[%clk 0:02:13.2]} 15... Bxc3+ {[%clk 0:02:16.2]} 16. Rxc3 {[%clk 0:02:12.2]} 16... Nb4 {[%clk 0:02:14.6]} 17. Bb3 {[%clk 0:01:57.9]} 17... Rfd8 {[%clk 0:02:03.2]} 18. O-O {[%clk 0:01:56.4]} 18... Bxf3 {[%clk 0:01:50.6]} 19. gxf3 {[%clk 0:01:55]} 19... Rd2 {[%clk 0:01:36.1]} 20. a3 {[%clk 0:01:51.3]} 20... Nc6 {[%clk 0:01:30.9]} 21. c5 {[%clk 0:01:47.8]} 21... Rad8 {[%clk 0:01:22.9]} 22. cxb6 {[%clk 0:01:43.8]} 22... Na5 {[%clk 0:01:22.4]} 23. Ba4 {[%clk 0:01:32.2]} 23... axb6 {[%clk 0:01:12.6]} 24. f4 {[%clk 0:01:21.8]} 24... exf4 {[%clk 0:01:09]} 25. exf4 {[%clk 0:01:20.9]} 25... g6 {[%clk 0:01:04.9]} 26. Ne7+ {[%clk 0:01:16.6]} 26... Kg7 {[%clk 0:01:04.2]} 27. Nc6 {[%clk 0:01:14.4]} 27... Nxc6 {[%clk 0:01:02]} 28. Rxc6 {[%clk 0:01:13.2]} 28... Ra8 {[%clk 0:00:53.5]} 29. Bb5 {[%clk 0:01:05.1]} 29... Rxa3 {[%clk 0:00:50.6]} 30. Rxb6 {[%clk 0:01:03.9]} 30... Rb3 {[%clk 0:00:50]} 31. Rc1 {[%clk 0:00:53.2]} 31... Rdb2 {[%clk 0:00:46.9]} 32. Rc5 {[%clk 0:00:51.7]} 32... Ne4 {[%clk 0:00:40.3]} 33. Re5 {[%clk 0:00:47.8]} 33... Nc3 {[%clk 0:00:36.6]} 34. Re3 {[%clk 0:00:25.6]} 34... Nxb5 {[%clk 0:00:31]} 35. Rxb3 {[%clk 0:00:18.9]} 35... Rxb3 {[%clk 0:00:30.9]} 36. Rc6 {[%clk 0:00:17.2]} 36... Rb1+ {[%clk 0:00:23]} 37. Kg2 {[%clk 0:00:14.2]} 37... Nd4 {[%clk 0:00:21.4]} 38. Rd6 {[%clk 0:00:12.2]} 38... Ne6 {[%clk 0:00:20.4]} 39. Rd4 {[%clk 0:00:10.6]} 39... Rb2 {[%clk 0:00:19.4]} 40. Rd3 {[%clk 0:00:08.9]} 40... Rb4 {[%clk 0:00:17.8]} 41. Re3 {[%clk 0:00:07.5]} 41... Rxf4 {[%clk 0:00:17.2]} 42. Rf3 {[%clk 0:00:06.4]} 42... Rxf3 {[%clk 0:00:16.4]} 43. Kxf3 {[%clk 0:00:05.8]} 43... Ng5+ {[%clk 0:00:15.8]} 44. Kg2 {[%clk 0:00:05.3]} 44... Kf6 {[%clk 0:00:15.2]} 45. Kg3 {[%clk 0:00:04.8]} 45... Ke5 {[%clk 0:00:14.8]} 46. h4 {[%clk 0:00:04.1]} 46... Ne4+ {[%clk 0:00:14.4]} 47. Kf3 {[%clk 0:00:03.3]} 47... f5 {[%clk 0:00:13.7]} 48. Kg2 {[%clk 0:00:00.9]} 48... Nf6 {[%clk 0:00:13.3]} 49. f3 {[%clk 0:00:00.1]} 49... f4 {[%clk 0:00:11.6]} 0-1\n",
            "time_control": "180",
            "end_time": 1741495367,
            "rated": true,
            "tcn": "lBZJgvYIjr0Scj5Qmu!TfmXPbl6XkAIBvB9Rlv8!acSKBLJArARzjs7dmdzscsQzdr97egXvov7liqzQAI47IPQGryWPvDKDuD2UL0!20QGQsQ74yH4qQPqrfcljcITCIKCsKusHurjrPQrbgoHBQRBSRBbjBtjztuzDuvDvovSMvo2TowTKpFMCwv1LvoCTnvLD",
            "uuid": "14767935-fca0-11ef-b33b-b4382c01000f",
            "initial_setup": "rnbqkbnr/pppppppp/8/8/8/8/PPPPPPPP/RNBQKBNR w KQkq - 0 1",
            "fen": "8/7p/5np1/4k3/5p1P/5P2/6K1/8 w - -",
            "time_class": "blitz",
            "rules": "chess",
            "white": {
                "rating": 808,
                "result": "timeout",
                "@id": "https://api.chess.com/pub/player/pitudoarana",
                "username": "pitudoArana",
                "uuid": "54ea4292-8db8-11ef-b747-0d5e53e2e65b"
            },
            "black": {
                "rating": 832,
                "result": "win",
                "@id": "https://api.chess.com/pub/player/jorgepr1",
                "username": "Jorgepr1",
                "uuid": "22e90e32-1d95-11eb-989c-891235857dcd"
            },
            "eco": "https://www.chess.com/openings/Colle-System...4.b3-c5-5.Bb2-Nc6"
        },
        {
            "url": "https://www.chess.com/game/live/136062558134",
            "pgn": "[Event \"Live Chess\"]\n[Site \"Chess.com\"]\n[Date \"2025.03.09\"]\n[Round \"-\"]\n[White \"Jorgepr1\"]\n[Black \"j1800collett\"]\n[Result \"1-0\"]\n[CurrentPosition \"7R/p7/8/5p2/7Q/4P3/PP4rk/1K1R4 b - -\"]\n[Timezone \"UTC\"]\n[ECO \"B32\"]\n[ECOUrl \"https://www.chess.com/openings/Sicilian-Defense-Open-Lowenthal-Variation-5.Nxc6-bxc6\"]\n[UTCDate \"2025.03.09\"]\n[UTCTime \"04:46:23\"]\n[WhiteElo \"881\"]\n[BlackElo \"851\"]\n[TimeControl \"60\"]\n[Termination \"Jorgepr1 won by checkmate\"]\n[StartTime \"04:46:23\"]\n[EndDate \"2025.03.09\"]\n[EndTime \"04:48:21\"]\n[Link \"https://www.chess.com/game/live/136062558134\"]\n\n1. e4 {[%clk 0:00:58.9]} 1... c5 {[%clk 0:00:59.1]} 2. Nf3 {[%clk 0:00:58.4]} 2... Nc6 {[%clk 0:00:58.3]} 3. d4 {[%clk 0:00:56.7]} 3... cxd4 {[%clk 0:00:57.2]} 4. Nxd4 {[%clk 0:00:56.6]} 4... e5 {[%clk 0:00:56]} 5. Nxc6 {[%clk 0:00:54.7]} 5... bxc6 {[%clk 0:00:55.9]} 6. Nc3 {[%clk 0:00:53.4]} 6... Bb7 {[%clk 0:00:54.5]} 7. Bc4 {[%clk 0:00:52.9]} 7... Bc5 {[%clk 0:00:53]} 8. Be3 {[%clk 0:00:51.3]} 8... Bxe3 {[%clk 0:00:51.2]} 9. fxe3 {[%clk 0:00:51.2]} 9... Qh4+ {[%clk 0:00:49]} 10. g3 {[%clk 0:00:49.5]} 10... Qh3 {[%clk 0:00:47.1]} 11. Qf3 {[%clk 0:00:46.9]} 11... f6 {[%clk 0:00:43.9]} 12. O-O-O {[%clk 0:00:46.1]} 12... Ne7 {[%clk 0:00:42.9]} 13. Kb1 {[%clk 0:00:41.8]} 13... d5 {[%clk 0:00:41.8]} 14. exd5 {[%clk 0:00:40.8]} 14... cxd5 {[%clk 0:00:41.1]} 15. Bxd5 {[%clk 0:00:39.4]} 15... Nxd5 {[%clk 0:00:40.3]} 16. Nxd5 {[%clk 0:00:37.6]} 16... O-O {[%clk 0:00:37.7]} 17. Ne7+ {[%clk 0:00:35.4]} 17... Kh8 {[%clk 0:00:35.8]} 18. Qxb7 {[%clk 0:00:34.9]} 18... Rab8 {[%clk 0:00:33.6]} 19. Qd5 {[%clk 0:00:31.9]} 19... Qc8 {[%clk 0:00:31]} 20. Nxc8 {[%clk 0:00:29.9]} 20... Rbxc8 {[%clk 0:00:29.1]} 21. Qd6 {[%clk 0:00:28.4]} 21... Rg8 {[%clk 0:00:27.7]} 22. Qd5 {[%clk 0:00:26.9]} 22... Rcf8 {[%clk 0:00:26.7]} 23. Rd3 {[%clk 0:00:26]} 23... h5 {[%clk 0:00:25.8]} 24. Rhd1 {[%clk 0:00:25.2]} 24... h4 {[%clk 0:00:24.8]} 25. c3 {[%clk 0:00:22.9]} 25... Kh7 {[%clk 0:00:24.2]} 26. gxh4 {[%clk 0:00:21.8]} 26... Kh6 {[%clk 0:00:22]} 27. c4 {[%clk 0:00:21.3]} 27... g5 {[%clk 0:00:21]} 28. c5 {[%clk 0:00:20.8]} 28... gxh4 {[%clk 0:00:20]} 29. c6 {[%clk 0:00:20]} 29... Kg5 {[%clk 0:00:19.2]} 30. Qc5 {[%clk 0:00:19]} 30... f5 {[%clk 0:00:17.7]} 31. Qxe5 {[%clk 0:00:17.7]} 31... Rc8 {[%clk 0:00:15.4]} 32. Qc5 {[%clk 0:00:16.9]} 32... Rg6 {[%clk 0:00:13.6]} 33. c7 {[%clk 0:00:16.2]} 33... Kg4 {[%clk 0:00:10.5]} 34. Rd8 {[%clk 0:00:15.6]} 34... Rxc7 {[%clk 0:00:09]} 35. Qxc7 {[%clk 0:00:14.1]} 35... Kh3 {[%clk 0:00:07.6]} 36. Qc4 {[%clk 0:00:14]} 36... Rg2 {[%clk 0:00:06.1]} 37. Rh8 {[%clk 0:00:11.5]} 37... Kxh2 {[%clk 0:00:04.8]} 38. Qxh4# {[%clk 0:00:11.1]} 1-0\n",
            "time_control": "60",
            "end_time": 1741495701,
            "rated": true,
            "tcn": "mCYIgv5QlBIBvB0KBQXQbs6XfA9IcuIunu7FowFxdv1Tec!0cbZJCJQJAJ0JsJ8!J0!?vX45XJx60656JR9!RJ69dt3NhdNFks?3wF3VsA2MAIMFIQVMJITLIK96KI!UQYMEt76YIYExYAUo7?xpAF",
            "uuid": "73b01b74-fca1-11ef-ac41-a9c46501000f",
            "initial_setup": "rnbqkbnr/pppppppp/8/8/8/8/PPPPPPPP/RNBQKBNR w KQkq - 0 1",
            "fen": "7R/p7/8/5p2/7Q/4P3/PP4rk/1K1R4 b - -",
            "time_class": "bullet",
            "rules": "chess",
            "white": {
                "rating": 881,
                "result": "win",
                "@id": "https://api.chess.com/pub/player/jorgepr1",
                "username": "Jorgepr1",
                "uuid": "22e90e32-1d95-11eb-989c-891235857dcd"
            },
            "black": {
                "rating": 851,
                "result": "checkmated",
                "@id": "https://api.chess.com/pub/player/j1800collett",
                "username": "j1800collett",
                "uuid": "8a56eee4-e84b-11ed-8f76-e9ea636af247"
            },
            "eco": "https://www.chess.com/openings/Sicilian-Defense-Open-Lowenthal-Variation-5.Nxc6-bxc6"
        }
    ]
}